Workbook

Sheet Quick Offers
B1: FULL REHAB | E1: FILL THIS OUT
B3: 70% of ARV | C3: =F3*0.7 -> 210000 | E3: ARV (after repair value) | F3: =K3 -> 300000 | G3: average of 3 comps | H3: 300000 | I3: 300000 | J3: 300000 | K3: =AVERAGE(H3:J3) -> 300000
B4: Assignment Fee | C4: -10000 | E4: Square Footage | F4: 2000
B5: All In Max Limit | C5: =sum(C3:C4) -> 200000 | E5: Full Rehab | F5: 150 | G5: per squre foot cost
B6: Repair Costs | C6: =-F4*F5 -> -300000 | E6: Medium Rehab | F6: 100 | G6: per squre foot cost
B7: Offer | C7: =sum(C5:C6) -> -100000 | E7: Light Rehab | F7: 60 | G7: per squre foot cost
B8: % of ARV | C8: =C7/F3 -> -0.33333333
D9: https://meet.google.com/qpi-ibwe-vzs
B10: MEDIUM REHAB
B12: 70% of ARV | C12: =F3*0.7 -> 210000
B13: Assignment Fee | C13: -10000 | E13: Value | F13: Desired Outcome | G13: Probability of Sale | H13: / | I13: Time (Months) | J13: Effort | K13: Value
B14: All In Max Limit | C14: =sum(C12:C13) -> 200000 | E14: Where they want | F14: =F3 -> 300000 | G14: 0.6 | I14: 1 | J14: 1 | K14: =F14*G14/(I14*J14) -> 180000
B15: Repair Costs | C15: =-F4*F6 -> -200000 | E15: Where they are | F15: =F3 -> 300000 | G15: 1 | I15: 5 | J15: 5 | K15: =F15*G15/(I15*J15) -> 12000
B16: Offer | C16: =sum(C14:C15) -> 0 | K16: =K14-K15 -> 168000
B17: % of ARV | C17: =C16/F3 -> 0
B19: LIGHT REHAB
B21: 70% of ARV | C21: =F3*0.7 -> 210000
B22: Assignment Fee | C22: -10000
B23: All In Max Limit | C23: =sum(C21:C22) -> 200000
B24: Repair Costs | C24: =-F4*F7 -> -120000
B25: Offer | C25: =sum(C23:C24) -> 80000
B26: % of ARV | C26: =C25/F3 -> 0.26666667

Sheet Aquisitions Deal Analyzer
B2: PROPERTY INFORMATION
B3: Property Address: | M3: 70% of ARV | N3: =E13*0.7 -> 210000
B4: Total Square Footage: | M4: Assignment Fee | N4: -10000
B5: # of Units | M5: All In Max Limit | N5: =sum(N3:N4) -> 200000
B6: Occupied? | M6: Repair Costs | N6: =-E12 -> -20050
M7: Offer | N7: =sum(N5:N6) -> 179950
B8: PROPERTY VALUES/PRICING | G8: DEAL SUMMARY & POTENTIAL PROFIT | M8: % of ARV | N8: =N7/E13 -> 0.59983333
B9: Estimated Hold Time months : | E9: 4
B10: Current "As-Is" Value: | E10: 200000 | G10: Total Financing Costs: | J10: =E32 -> 15333.333 | M10: ROI
B11: Purchase Price: | E11: 200000 | G11: Total Holding Costs | J11: =J32 -> 7633.3333 | M11: Cash Invested | N11: =J10+J11 -> 22966.667
B12: Estimated Repair Costs: | E12: 20050 | G12: Total Buying Transaction Costs: | J12: =sum(F37:F39) -> 4500 | M12: Cash Return | N12: =J14 -> 44453.333
B13: After Repair Value: | E13: 300000 | G13: Total Selling Transaction Costs: | J13: =sum(F42:F49) -> 8030 | M13: ROI on Cash | N13: =N12/N11 -> 1.9355588
B14: PURCHSE AND REPAIR COSTS: | E14: =-sum(E11:F12) -> -220050 | G14: ESTIMATED NET PROFIT: | J14: =E13-(E11+E12+J10+J11+J12+J13) -> 44453.333 | M14: Time to Return | N14: =CONCATENATE(E9," Months") -> 4 Months
B17: FINANCING PROJECTION | G17: HOLDING COSTS
E18: Rate | F18: Amount Paid | J18: Monthly | K18: Annualized
B19: First Mortgage / Lien Amount: | E19: 200000 | G19: Property Taxes | J19: 0.0875 | K19: =((J19*E10)/12)*E9 -> 5833.3333
B20: First Mortgage Points: | E20: 0.03 | F20: =E20*$E$19 -> 6000 | G20: HOA & Condo Fees | J20: 0 | K20: =J20*E9 -> 0
B21: First Mortgage Interest: | E21: 0 | F21: =E21*E19*E9 -> 0 | G21: Insurance Costs | J21: 100 | K21: =J21*$E$9 -> 400
B22: First Mortgage Monthly Interest Only Payment: | E22: =0.14/12 -> 0.011666667 | F22: =E22*E19*E9 -> 9333.3333 | G22: Utilities | J22: 0 | K22: =J22*$E$9 -> 0
B23: Second Mortgage / Lien Amount: | E23: 0 | G23: Gas | J23: 150 | K23: =J23*$E$9 -> 600
B24: Second Mortgage Points: | E24: 0.1 | F24: =E24*$E$23 -> 0 | G24: Water | J24: 100 | K24: =J24*$E$9 -> 400
B25: Second Mortgage Interest: | E25: 0 | F25: =E25*$E$23 -> 0 | G25: Electricity | J25: 100 | K25: =J25*$E$9 -> 400
B26: Second Mortgage Monthly Interest Only Payment: | E26: 0 | F26: =E26*$E$23*E9 -> 0 | G26: Miscellaneous | K26: =J26*E9 -> 0
B27: Misc. Mortgage / Lien Amount: | F27: 0 | G27: Total Maintenance Costs | J27: =sum(K19:K26) -> 7633.3333
B28: Misc. Mortgage Points: | F28: 0 | G28: Miscellaneous Holding Costs | K28: =$E$9*J28 -> 0
B29: Misc. Mortgage Interest: | F29: 0 | G29: Miscellaneous Holding Costs | K29: =$E$9*J29 -> 0
B30: Misc. Mortgage Monthly Interest Only Payment: | F30: 0 | G30: Miscellaneous Holding Costs | K30: =$E$9*J30 -> 0
B31: Miscellaneous Financing Costs: | F31: 0 | G31: Miscellaneous Holding Costs | K31: =$E$9*J31 -> 0
B32: TOTAL FINANCING COSTS: | E32: =sum(F19:F31) -> 15333.333 | G32: TOTAL HOLDING COSTS: | J32: =sum(K19:K31) -> 7633.3333
B35: BUYING TRANSACTION COSTS | G35: NOTES
E36: % of Price | F36: Total
B37: Escrow / Attorney Fees | E37: 0.005 | F37: =E37*$E$13 -> 1500 | G37: Expected ROI in Delayed Draw Scenario | I37: Cash to Cover Delayed Draw | J37: Actual Delayed Draw ROI
B38: Title Insurance / Search Costs | E38: 0.01 | F38: =E38*$E$13 -> 3000
B39: Miscellaneous Buying Costs | E39: 0 | F39: =E39*$E$13 -> 0 | G39: Cash Invested | H39: =J10+J11 -> 22966.667 | I39: =-if(min('Delayed Draw Cash Flow'!H6:H41)<0,min('Delayed Draw Cash Flow'!H6:H41),0) -> 3246.875 | J39: =Sum(H39:I39) -> 26213.542
B40: SELLING TRANSACTION COSTS | G40: Cash Return | H40: =J14 -> 44453.333 | J40: =H40 -> 44453.333
E41: % of Price | F41: Total | G41: ROI on Cash | H41: =H40/H39 -> 1.9355588 | J41: =J40/J39 -> 1.6958156
B42: Escrow / Attorney Fees | E42: 0.005 | F42: =E42*$E$13 -> 1500 | G42: Time to Return | H42: =CONCATENATE(E9," Months") -> 4 Months | J42: =CONCATENATE(E9," Months") -> 4 Months
B43: Selling Recording Fees | E43: 0.0025 | F43: =E43*$E$11 -> 500
B44: Realtor Fees | E44: 0.03 | F44: =E44*$E$11 -> 6000 | G44: Expected ROI in Up Front Draw Scenario | I44: Cash to Cover Up Front Draw | J44: Actual Upfront Draw ROI
B45: Transfer & Conveyance Fees | E45: 0.0001 | F45: =E45*$E$13 -> 30
B46: Home Warranty | F46: 0 | G46: Cash Invested | H46: =J10+J11 -> 22966.667 | I46: =-if(min('Up Front Draw Cash Flow'!H6:H41)<0,min('Up Front Draw Cash Flow'!H6:H41),min('Up Front Draw Cash Flow'!H6:H41)) -> 3246.875 | J46: =sum(H46:I46) -> 26213.542
B47: Staging Costs | F47: 0 | G47: Cash Return | H47: =J14 -> 44453.333 | J47: =H47 -> 44453.333
B48: Marketing Costs | F48: 0 | G48: ROI on Cash | H48: =H40/H39 -> 1.9355588 | J48: =J47/J46 -> 1.6958156
B49: Miscellaneous Selling Costs | F49: 0 | G49: Time to Return | H49: =CONCATENATE(E9," Months") -> 4 Months | J49: =CONCATENATE(E9," Months") -> 4 Months

Sheet Delayed Draw Cash Flow
A1: DELAYED DRAW CASH FLOW SCHEDULE | K1: COSTS | L1: Construction Costs | M1: Purchase Price | N1: First Mortgage Points: | O1: First Mortgage Interest: | P1: First Mortgage Monthly Interest Only Payment: | Q1: Property Taxes | R1: HOA & Condo Fees | S1: Insurance Costs | T1: Utilities | X1: Buying Transaction Costs | AA1: Selling Transaction Costs | AF1: Staging Costs | AG1: Marketing Costs | AH1: Miscellaneous Selling Costs
A2: THE NUMBERS IN BLUE ARE AUTOMATICALLY CALCULATED. THE BOXES HIGHLIGHTED IN YELLOW ARE MEANT FOR YOU TO FILL OUT! | T2: Gas | U2: Water | V2: Electricity | W2: Miscellaneous | X2: Escrow / Attorney Fees | Y2: Title Insurance/Search Costs | Z2: Miscellaneous Buying Costs | AA2: Escrow / Attorney Fees | AB2: Selling Recording Fees | AC2: Realtor Fees | AD2: Transfer & Conveyance Fees | AE2: Home Warranty
B3: Net Cash In---> | C3: =sum(D6:D43) -> 300000 | F3: Duration Weeks | G3: Beginning Cash Balance ---> | H3: ='Aquisitions Deal Analyzer'!H39 -> 22966.667 | I3: Net Cash Out Below | K3: Estimated Total Costs | L3: ='Aquisitions Deal Analyzer'!E12 -> 20050 | M3: ='Aquisitions Deal Analyzer'!E11 -> 200000 | N3: ='Aquisitions Deal Analyzer'!F20 -> 6000 | O3: ='Aquisitions Deal Analyzer'!F21 -> 0 | P3: ='Aquisitions Deal Analyzer'!F22 -> 9333.3333 | Q3: ='Aquisitions Deal Analyzer'!K19 -> 5833.3333 | R3: ='Aquisitions Deal Analyzer'!K20 -> 0 | S3: ='Aquisitions Deal Analyzer'!K21 -> 400 | T3: ='Aquisitions Deal Analyzer'!K23 -> 600 | U3: ='Aquisitions Deal Analyzer'!K24 -> 400 | V3: ='Aquisitions Deal Analyzer'!K25 -> 400 | W3: ='Aquisitions Deal Analyzer'!K26 -> 0 | X3: ='Aquisitions Deal Analyzer'!F37 -> 1500 | Y3: ='Aquisitions Deal Analyzer'!F38 -> 3000 | Z3: ='Aquisitions Deal Analyzer'!F39 -> 0 | AA3: ='Aquisitions Deal Analyzer'!F42 -> 1500 | AB3: ='Aquisitions Deal Analyzer'!F43 -> 500 | AC3: ='Aquisitions Deal Analyzer'!F44 -> 6000 | AD3: ='Aquisitions Deal Analyzer'!F45 -> 30 | AE3: ='Aquisitions Deal Analyzer'!F46 -> 0 | AF3: ='Aquisitions Deal Analyzer'!F47 -> 0 | AG3: ='Aquisitions Deal Analyzer'!F48 -> 0 | AH3: ='Aquisitions Deal Analyzer'!F49 -> 0
F4: ='Aquisitions Deal Analyzer'!E9*4 -> 16 | I4: =sum(I6:I41) -> 255546.67 | K4: Frequency | L4: Weekly | M4: One Time | N4: One Time | O4: Monthly | P4: Monthly | Q4: One Time | R4: One Time | S4: Monthly | T4: Monthly | U4: Monthly | V4: Monthly | W4: Monthly | X4: One Time | Y4: One Time | Z4: One Time | AA4: One Time | AB4: One Time | AC4: One Time | AD4: One Time | AE4: One Time | AF4: One Time | AG4: One Time | AH4: One Time
B5: Cash In Source | C5: Week | D5: Amount | F5: Week | G5: Cash In to the Project During this Week | H5: Balance @ End of Week | I5: Expenses Required | K5: Week
B6: Lender Purchase Loan | C6: 1 | D6: ='Aquisitions Deal Analyzer'!E11 -> 200000 | F6: 1 | G6: =sumif($C$6:$C44,F6,$D$6:$D44) -> 200000 | H6: =H4+H3-I6+G6 -> 2596.875 | I6: =sum(L6:AH6) -> 220369.79 | K6: 1 | L6: =L3/(F4) -> 1253.125 | M6: =M3 -> 200000 | N6: =N3 -> 6000 | O6: =O3/('Aquisitions Deal Analyzer'!$E$9) -> 0 | P6: =P3/('Aquisitions Deal Analyzer'!$E$9) -> 2333.3333 | Q6: =Q3 -> 5833.3333 | R6: =R3 -> 0 | S6: =S3/('Aquisitions Deal Analyzer'!$E$9) -> 100 | T6: =T3/('Aquisitions Deal Analyzer'!$E$9) -> 150 | U6: =U3/('Aquisitions Deal Analyzer'!$E$9) -> 100 | V6: =V3/('Aquisitions Deal Analyzer'!$E$9) -> 100 | W6: =W3/('Aquisitions Deal Analyzer'!$E$9) -> 0 | X6: =X3 -> 1500 | Y6: =Y3 -> 3000 | Z6: =Z3 -> 0 | AA6: =if($K6=$F$4,AA$3,0) -> 0 | AB6: =if($K6=$F$4,AB$3,0) -> 0 | AC6: =if($K6=$F$4,AC$3,0) -> 0 | AD6: =if($K6=$F$4,AD$3,0) -> 0 | AE6: =if($K6=$F$4,AE$3,0) -> 0 | AF6: =if($K6=$F$4,AF$3,0) -> 0 | AG6: =if($K6=$F$4,AG$3,0) -> 0 | AH6: =if($K6=$F$4,AH$3,0) -> 0
B7: Lender Draw 1 at 25% | C7: =F4*E7 -> 4 | D7: ='Aquisitions Deal Analyzer'!$E$12/3 -> 6683.3333 | E7: 0.25 | F7: 2 | G7: =sumif($C$6:$C45,F7,$D$6:$D45) -> 0 | H7: =H6-I7+G7 -> 1343.75 | I7: =sum(L7:AH7) -> 1253.125 | K7: 2 | L7: =if((L3-L6)>0.1,L6,0) -> 1253.125 | O7: 0 | P7: 0 | S7: 0 | T7: 0 | U7: 0 | V7: 0 | W7: 0 | AA7: =if($K7=$F$4,AA$3,0) -> 0 | AB7: =if($K7=$F$4,AB$3,0) -> 0 | AC7: =if($K7=$F$4,AC$3,0) -> 0 | AD7: =if($K7=$F$4,AD$3,0) -> 0 | AE7: =if($K7=$F$4,AE$3,0) -> 0 | AF7: =if($K7=$F$4,AF$3,0) -> 0 | AG7: =if($K7=$F$4,AG$3,0) -> 0 | AH7: =if($K7=$F$4,AH$3,0) -> 0
B8: Lender Draw 2 at 50% | C8: =F4*E8 -> 8 | D8: ='Aquisitions Deal Analyzer'!$E$12/3 -> 6683.3333 | E8: 0.5 | F8: 3 | G8: =sumif($C$6:$C46,F8,$D$6:$D46) -> 0 | H8: =H7-I8+G8 -> 90.625 | I8: =sum(L8:AH8) -> 1253.125 | K8: 3 | L8: =if((L3-L6-L7)>0.1,L7,0) -> 1253.125 | O8: 0 | P8: 0 | S8: 0 | T8: 0 | U8: 0 | V8: 0 | W8: 0 | AA8: =if($K8=$F$4,AA$3,0) -> 0 | AB8: =if($K8=$F$4,AB$3,0) -> 0 | AC8: =if($K8=$F$4,AC$3,0) -> 0 | AD8: =if($K8=$F$4,AD$3,0) -> 0 | AE8: =if($K8=$F$4,AE$3,0) -> 0 | AF8: =if($K8=$F$4,AF$3,0) -> 0 | AG8: =if($K8=$F$4,AG$3,0) -> 0 | AH8: =if($K8=$F$4,AH$3,0) -> 0
B9: Lender Draw 3 at 75% | C9: =F4*E9 -> 12 | D9: ='Aquisitions Deal Analyzer'!$E$12/3 -> 6683.3333 | E9: 0.75 | F9: 4 | G9: =sumif($C$6:$C47,F9,$D$6:$D47) -> 6683.3333 | H9: =H8-I9+G9 -> 5520.8333 | I9: =sum(L9:AH9) -> 1253.125 | K9: 4 | L9: =if((L3-L6-L7-L8)>0.1,L8,0) -> 1253.125 | O9: 0 | P9: 0 | S9: 0 | T9: 0 | U9: 0 | V9: 0 | W9: 0 | AA9: =if($K9=$F$4,AA$3,0) -> 0 | AB9: =if($K9=$F$4,AB$3,0) -> 0 | AC9: =if($K9=$F$4,AC$3,0) -> 0 | AD9: =if($K9=$F$4,AD$3,0) -> 0 | AE9: =if($K9=$F$4,AE$3,0) -> 0 | AF9: =if($K9=$F$4,AF$3,0) -> 0 | AG9: =if($K9=$F$4,AG$3,0) -> 0 | AH9: =if($K9=$F$4,AH$3,0) -> 0
B10: Property Sale | C10: =F4 -> 16 | D10: ='Aquisitions Deal Analyzer'!E13 -> 300000 | F10: 5 | G10: =sumif($C$6:$C48,F10,$D$6:$D48) -> 0 | H10: =H9-I10+G10 -> 1484.375 | I10: =sum(L10:AH10) -> 4036.4583 | K10: 5 | L10: =if((L3-L6-L7-L8-L9)>0.1,L9,0) -> 1253.125 | O10: =if((O3-O6)>0.1,O6,0) -> 0 | P10: =if((P3-P6)>0.1,P6,0) -> 2333.3333 | S10: =if((S3-S6)>0.1,S6,0) -> 100 | T10: =if((T3-T6)>0.1,T6,0) -> 150 | U10: =if((U3-U6)>0.1,U6,0) -> 100 | V10: =if((V3-V6)>0.1,V6,0) -> 100 | W10: =if((W3-W6)>0.1,W6,0) -> 0 | AA10: =if($K10=$F$4,AA$3,0) -> 0 | AB10: =if($K10=$F$4,AB$3,0) -> 0 | AC10: =if($K10=$F$4,AC$3,0) -> 0 | AD10: =if($K10=$F$4,AD$3,0) -> 0 | AE10: =if($K10=$F$4,AE$3,0) -> 0 | AF10: =if($K10=$F$4,AF$3,0) -> 0 | AG10: =if($K10=$F$4,AG$3,0) -> 0 | AH10: =if($K10=$F$4,AH$3,0) -> 0
B11: Purchase Loan Repayment | C11: =F4 -> 16 | D11: =-'Aquisitions Deal Analyzer'!E11 -> -200000 | F11: 6 | G11: =sumif($C$6:$C49,F11,$D$6:$D49) -> 0 | H11: =H10-I11+G11 -> 231.25 | I11: =sum(L11:AH11) -> 1253.125 | K11: 6 | L11: =if((L3-L6-L7-L8-L9-L10)>0.1,L10,0) -> 1253.125 | O11: 0 | P11: 0 | S11: 0 | T11: 0 | U11: 0 | V11: 0 | W11: 0 | AA11: =if($K11=$F$4,AA$3,0) -> 0 | AB11: =if($K11=$F$4,AB$3,0) -> 0 | AC11: =if($K11=$F$4,AC$3,0) -> 0 | AD11: =if($K11=$F$4,AD$3,0) -> 0 | AE11: =if($K11=$F$4,AE$3,0) -> 0 | AF11: =if($K11=$F$4,AF$3,0) -> 0 | AG11: =if($K11=$F$4,AG$3,0) -> 0 | AH11: =if($K11=$F$4,AH$3,0) -> 0
B12: Construction Loan Repayment | C12: =F4 -> 16 | D12: =-'Aquisitions Deal Analyzer'!E12 -> -20050 | F12: 7 | G12: =sumif($C$6:$C50,F12,$D$6:$D50) -> 0 | H12: =H11-I12+G12 -> -1021.875 | I12: =sum(L12:AH12) -> 1253.125 | K12: 7 | L12: =if((L3-L6-L7-L8-L9-L10-L11)>0.1,L11,0) -> 1253.125 | O12: 0 | P12: 0 | S12: 0 | T12: 0 | U12: 0 | V12: 0 | W12: 0 | AA12: =if($K12=$F$4,AA$3,0) -> 0 | AB12: =if($K12=$F$4,AB$3,0) -> 0 | AC12: =if($K12=$F$4,AC$3,0) -> 0 | AD12: =if($K12=$F$4,AD$3,0) -> 0 | AE12: =if($K12=$F$4,AE$3,0) -> 0 | AF12: =if($K12=$F$4,AF$3,0) -> 0 | AG12: =if($K12=$F$4,AG$3,0) -> 0 | AH12: =if($K12=$F$4,AH$3,0) -> 0
B13: Other Expense 1 | F13: 8 | G13: =sumif($C$6:$C51,F13,$D$6:$D51) -> 6683.3333 | H13: =H12-I13+G13 -> 4408.3333 | I13: =sum(L13:AH13) -> 1253.125 | K13: 8 | L13: =if((L3-L6-L7-L8-L9-L10-L11-L12)>0.1,L12,0) -> 1253.125 | O13: 0 | P13: 0 | S13: 0 | T13: 0 | U13: 0 | V13: 0 | W13: 0 | AA13: =if($K13=$F$4,AA$3,0) -> 0 | AB13: =if($K13=$F$4,AB$3,0) -> 0 | AC13: =if($K13=$F$4,AC$3,0) -> 0 | AD13: =if($K13=$F$4,AD$3,0) -> 0 | AE13: =if($K13=$F$4,AE$3,0) -> 0 | AF13: =if($K13=$F$4,AF$3,0) -> 0 | AG13: =if($K13=$F$4,AG$3,0) -> 0 | AH13: =if($K13=$F$4,AH$3,0) -> 0
B14: Other Expense 2 | F14: 9 | G14: =sumif($C$6:$C52,F14,$D$6:$D52) -> 0 | H14: =H13-I14+G14 -> 371.875 | I14: =sum(L14:AH14) -> 4036.4583 | K14: 9 | L14: =if((L3-L6-L7-L8-L9-L10-L11-L12-L13)>0.1,L13,0) -> 1253.125 | O14: =if((O3-O6-O10)>0.1,O10,0) -> 0 | P14: =if((P3-P6-P10)>0.1,P10,0) -> 2333.3333 | S14: =if((S3-S6-S10)>0.1,S10,0) -> 100 | T14: =if((T3-T6-T10)>0.1,T10,0) -> 150 | U14: =if((U3-U6-U10)>0.1,U10,0) -> 100 | V14: =if((V3-V6-V10)>0.1,V10,0) -> 100 | W14: =if((W3-W6-W10)>0.1,W10,0) -> 0 | AA14: =if($K14=$F$4,AA$3,0) -> 0 | AB14: =if($K14=$F$4,AB$3,0) -> 0 | AC14: =if($K14=$F$4,AC$3,0) -> 0 | AD14: =if($K14=$F$4,AD$3,0) -> 0 | AE14: =if($K14=$F$4,AE$3,0) -> 0 | AF14: =if($K14=$F$4,AF$3,0) -> 0 | AG14: =if($K14=$F$4,AG$3,0) -> 0 | AH14: =if($K14=$F$4,AH$3,0) -> 0
B15: Other Expense 3 | F15: 10 | G15: =sumif($C$6:$C53,F15,$D$6:$D53) -> 0 | H15: =H14-I15+G15 -> -881.25 | I15: =sum(L15:AH15) -> 1253.125 | K15: 10 | L15: =if((L3-L6-L7-L8-L9-L10-L11-L12-L13-L14)>0.1,L14,0) -> 1253.125 | O15: 0 | P15: 0 | S15: 0 | T15: 0 | U15: 0 | V15: 0 | W15: 0 | AA15: =if($K15=$F$4,AA$3,0) -> 0 | AB15: =if($K15=$F$4,AB$3,0) -> 0 | AC15: =if($K15=$F$4,AC$3,0) -> 0 | AD15: =if($K15=$F$4,AD$3,0) -> 0 | AE15: =if($K15=$F$4,AE$3,0) -> 0 | AF15: =if($K15=$F$4,AF$3,0) -> 0 | AG15: =if($K15=$F$4,AG$3,0) -> 0 | AH15: =if($K15=$F$4,AH$3,0) -> 0
B16: Other Expense 4 | F16: 11 | G16: =sumif($C$6:$C54,F16,$D$6:$D54) -> 0 | H16: =H15-I16+G16 -> -2134.375 | I16: =sum(L16:AH16) -> 1253.125 | K16: 11 | L16: =if((L3-L6-L7-L8-L9-L10-L11-L12-L13-L14-15)>0.1,L15,0) -> 1253.125 | O16: 0 | P16: 0 | S16: 0 | T16: 0 | U16: 0 | V16: 0 | W16: 0 | AA16: =if($K16=$F$4,AA$3,0) -> 0 | AB16: =if($K16=$F$4,AB$3,0) -> 0 | AC16: =if($K16=$F$4,AC$3,0) -> 0 | AD16: =if($K16=$F$4,AD$3,0) -> 0 | AE16: =if($K16=$F$4,AE$3,0) -> 0 | AF16: =if($K16=$F$4,AF$3,0) -> 0 | AG16: =if($K16=$F$4,AG$3,0) -> 0 | AH16: =if($K16=$F$4,AH$3,0) -> 0
B17: Other Expense 5 | F17: 12 | G17: =sumif($C$6:$C55,F17,$D$6:$D55) -> 6683.3333 | H17: =H16-I17+G17 -> 3295.8333 | I17: =sum(L17:AH17) -> 1253.125 | K17: 12 | L17: =if((L3-L6-L7-L8-L9-L10-L11-L12-L13-L14-L15-L16)>0.1,L16,0) -> 1253.125 | O17: 0 | P17: 0 | S17: 0 | T17: 0 | U17: 0 | V17: 0 | W17: 0 | AA17: =if($K17=$F$4,AA$3,0) -> 0 | AB17: =if($K17=$F$4,AB$3,0) -> 0 | AC17: =if($K17=$F$4,AC$3,0) -> 0 | AD17: =if($K17=$F$4,AD$3,0) -> 0 | AE17: =if($K17=$F$4,AE$3,0) -> 0 | AF17: =if($K17=$F$4,AF$3,0) -> 0 | AG17: =if($K17=$F$4,AG$3,0) -> 0 | AH17: =if($K17=$F$4,AH$3,0) -> 0
F18: 13 | G18: =sumif($C$6:$C56,F18,$D$6:$D56) -> 0 | H18: =H17-I18+G18 -> -740.625 | I18: =sum(L18:AH18) -> 4036.4583 | K18: 13 | L18: =if((L3-L6-L7-L8-L9-L10-L11-L12-L13-L14-L15-L16-L17)>0.1,L17,0) -> 1253.125 | O18: =if((O3-O6-O10-O14)>0.1,O14,0) -> 0 | P18: =if((P3-P6-P10-P14)>0.1,P14,0) -> 2333.3333 | S18: =if((S3-S6-S10-S14)>0.1,S14,0) -> 100 | T18: =if((T3-T6-T10-T14)>0.1,T14,0) -> 150 | U18: =if((U3-U6-U10-U14)>0.1,U14,0) -> 100 | V18: =if((V3-V6-V10-V14)>0.1,V14,0) -> 100 | W18: =if((W3-W6-W10-W14)>0.1,W14,0) -> 0 | AA18: =if($K18=$F$4,AA$3,0) -> 0 | AB18: =if($K18=$F$4,AB$3,0) -> 0 | AC18: =if($K18=$F$4,AC$3,0) -> 0 | AD18: =if($K18=$F$4,AD$3,0) -> 0 | AE18: =if($K18=$F$4,AE$3,0) -> 0 | AF18: =if($K18=$F$4,AF$3,0) -> 0 | AG18: =if($K18=$F$4,AG$3,0) -> 0 | AH18: =if($K18=$F$4,AH$3,0) -> 0
F19: 14 | G19: =sumif($C$6:$C57,F19,$D$6:$D57) -> 0 | H19: =H18-I19+G19 -> -1993.75 | I19: =sum(L19:AH19) -> 1253.125 | K19: 14 | L19: =if((L3-L6-L7-L8-L9-L10-L11-L12-L13-L14-L15-L16-L17-L18)>0.1,L18,0) -> 1253.125 | O19: 0 | P19: 0 | S19: 0 | T19: 0 | U19: 0 | V19: 0 | W19: 0 | AA19: =if($K19=$F$4,AA$3,0) -> 0 | AB19: =if($K19=$F$4,AB$3,0) -> 0 | AC19: =if($K19=$F$4,AC$3,0) -> 0 | AD19: =if($K19=$F$4,AD$3,0) -> 0 | AE19: =if($K19=$F$4,AE$3,0) -> 0 | AF19: =if($K19=$F$4,AF$3,0) -> 0 | AG19: =if($K19=$F$4,AG$3,0) -> 0 | AH19: =if($K19=$F$4,AH$3,0) -> 0
F20: 15 | G20: =sumif($C$6:$C58,F20,$D$6:$D58) -> 0 | H20: =H19-I20+G20 -> -3246.875 | I20: =sum(L20:AH20) -> 1253.125 | K20: 15 | L20: =if((L3-L6-L7-L8-L9-L10-L11-L12-L13-L14-L15-L16-L17-L18-L19)>0.1,L19,0) -> 1253.125 | O20: 0 | P20: 0 | S20: 0 | T20: 0 | U20: 0 | V20: 0 | W20: 0 | AA20: =if($K20=$F$4,AA$3,0) -> 0 | AB20: =if($K20=$F$4,AB$3,0) -> 0 | AC20: =if($K20=$F$4,AC$3,0) -> 0 | AD20: =if($K20=$F$4,AD$3,0) -> 0 | AE20: =if($K20=$F$4,AE$3,0) -> 0 | AF20: =if($K20=$F$4,AF$3,0) -> 0 | AG20: =if($K20=$F$4,AG$3,0) -> 0 | AH20: =if($K20=$F$4,AH$3,0) -> 0
F21: 16 | G21: =sumif($C$6:$C59,F21,$D$6:$D59) -> 79950 | H21: =H20-I21+G21 -> 67420 | I21: =sum(L21:AH21) -> 9283.125 | K21: 16 | L21: =if((L3-L6-L7-L8-L9-L10-L11-L12-L13-L14-L15-L16-L17-L18-L19-L20)>0.1,L20,0) -> 1253.125 | O21: 0 | P21: 0 | S21: 0 | T21: 0 | U21: 0 | V21: 0 | W21: 0 | AA21: =if($K21=$F$4,AA$3,0) -> 1500 | AB21: =if($K21=$F$4,AB$3,0) -> 500 | AC21: =if($K21=$F$4,AC$3,0) -> 6000 | AD21: =if($K21=$F$4,AD$3,0) -> 30 | AE21: =if($K21=$F$4,AE$3,0) -> 0 | AF21: =if($K21=$F$4,AF$3,0) -> 0 | AG21: =if($K21=$F$4,AG$3,0) -> 0 | AH21: =if($K21=$F$4,AH$3,0) -> 0
F22: 17 | G22: =sumif($C$6:$C60,F22,$D$6:$D60) -> 0 | H22: =H21-I22+G22 -> 67420 | I22: =sum(L22:AH22) -> 0 | K22: 17 | L22: =if((L3-L6-L7-L8-L9-L10-L11-L12-L13-L14-L15-L16-L17-L18-L19-L20-L21)>0.1,L21,0) -> 0 | O22: =if((O3-O6-O10-O14-O18)>0.1,O18,0) -> 0 | P22: =if((P3-P6-P10-P14-P18)>0.1,P18,0) -> 0 | S22: =if((S3-S6-S10-S14-S18)>0.1,S18,0) -> 0 | T22: =if((T3-T6-T10-T14-T18)>0.1,T18,0) -> 0 | U22: =if((U3-U6-U10-U14-U18)>0.1,U18,0) -> 0 | V22: =if((V3-V6-V10-V14-V18)>0.1,V18,0) -> 0 | W22: =if((W3-W6-W10-W14-W18)>0.1,W18,0) -> 0 | AA22: =if($K22=$F$4,AA$3,0) -> 0 | AB22: =if($K22=$F$4,AB$3,0) -> 0 | AC22: =if($K22=$F$4,AC$3,0) -> 0 | AD22: =if($K22=$F$4,AD$3,0) -> 0 | AE22: =if($K22=$F$4,AE$3,0) -> 0 | AF22: =if($K22=$F$4,AF$3,0) -> 0 | AG22: =if($K22=$F$4,AG$3,0) -> 0 | AH22: =if($K22=$F$4,AH$3,0) -> 0
F23: 18 | G23: =sumif($C$6:$C61,F23,$D$6:$D61) -> 0 | H23: =H22-I23+G23 -> 67420 | I23: =sum(L23:AH23) -> 0 | K23: 18 | L23: =if((L3-L6-L7-L8-L9-L10-L11-L12-L13-L14-L15-L16-L17-L18-L19-L20-L21-L22)>0.1,L22,0) -> 0 | O23: 0 | P23: 0 | S23: 0 | T23: 0 | U23: 0 | V23: 0 | W23: 0 | AA23: =if($K23=$F$4,AA$3,0) -> 0 | AB23: =if($K23=$F$4,AB$3,0) -> 0 | AC23: =if($K23=$F$4,AC$3,0) -> 0 | AD23: =if($K23=$F$4,AD$3,0) -> 0 | AE23: =if($K23=$F$4,AE$3,0) -> 0 | AF23: =if($K23=$F$4,AF$3,0) -> 0 | AG23: =if($K23=$F$4,AG$3,0) -> 0 | AH23: =if($K23=$F$4,AH$3,0) -> 0
F24: 19 | G24: =sumif($C$6:$C62,F24,$D$6:$D62) -> 0 | H24: =H23-I24+G24 -> 67420 | I24: =sum(L24:AH24) -> 0 | K24: 19 | L24: =if((L3-L6-L7-L8-L9-L10-L11-L12-L13-L14-L15-L16-L17-L18-L19-L20-L21-L22-L23)>0.1,L23,0) -> 0 | O24: 0 | P24: 0 | S24: 0 | T24: 0 | U24: 0 | V24: 0 | W24: 0 | AA24: =if($K24=$F$4,AA$3,0) -> 0 | AB24: =if($K24=$F$4,AB$3,0) -> 0 | AC24: =if($K24=$F$4,AC$3,0) -> 0 | AD24: =if($K24=$F$4,AD$3,0) -> 0 | AE24: =if($K24=$F$4,AE$3,0) -> 0 | AF24: =if($K24=$F$4,AF$3,0) -> 0 | AG24: =if($K24=$F$4,AG$3,0) -> 0 | AH24: =if($K24=$F$4,AH$3,0) -> 0
F25: 20 | G25: =sumif($C$6:$C63,F25,$D$6:$D63) -> 0 | H25: =H24-I25+G25 -> 67420 | I25: =sum(L25:AH25) -> 0 | K25: 20 | L25: =if((L3-L6-L7-L8-L9-L10-L11-L12-L13-L14-L15-L16-L17-L18-L19-L20-L21-L22-L23-L24)>0.1,L24,0) -> 0 | O25: 0 | P25: 0 | S25: 0 | T25: 0 | U25: 0 | V25: 0 | W25: 0 | AA25: =if($K25=$F$4,AA$3,0) -> 0 | AB25: =if($K25=$F$4,AB$3,0) -> 0 | AC25: =if($K25=$F$4,AC$3,0) -> 0 | AD25: =if($K25=$F$4,AD$3,0) -> 0 | AE25: =if($K25=$F$4,AE$3,0) -> 0 | AF25: =if($K25=$F$4,AF$3,0) -> 0 | AG25: =if($K25=$F$4,AG$3,0) -> 0 | AH25: =if($K25=$F$4,AH$3,0) -> 0
F26: 21 | G26: =sumif($C$6:$C64,F26,$D$6:$D64) -> 0 | H26: =H25-I26+G26 -> 67420 | I26: =sum(L26:AH26) -> 0 | K26: 21 | L26: =if((L3-L6-L7-L8-L9-L10-L11-L12-L13-L14-L15-L16-L17-L18-L19-L20-L21-L22-L23-L24-L25)>0.1,L25,0) -> 0 | O26: =if((O3-O6-O10-O14-O18-O22)>0.1,O22,0) -> 0 | P26: =if((P3-P6-P10-P14-P18-P22)>0.1,P22,0) -> 0 | S26: =if((S3-S6-S10-S14-S18-S22)>0.1,S22,0) -> 0 | T26: =if((T3-T6-T10-T14-T18-T22)>0.1,T22,0) -> 0 | U26: =if((U3-U6-U10-U14-U18-U22)>0.1,U22,0) -> 0 | V26: =if((V3-V6-V10-V14-V18-V22)>0.1,V22,0) -> 0 | W26: =if((W3-W6-W10-W14-W18-W22)>0.1,W22,0) -> 0 | AA26: =if($K26=$F$4,AA$3,0) -> 0 | AB26: =if($K26=$F$4,AB$3,0) -> 0 | AC26: =if($K26=$F$4,AC$3,0) -> 0 | AD26: =if($K26=$F$4,AD$3,0) -> 0 | AE26: =if($K26=$F$4,AE$3,0) -> 0 | AF26: =if($K26=$F$4,AF$3,0) -> 0 | AG26: =if($K26=$F$4,AG$3,0) -> 0 | AH26: =if($K26=$F$4,AH$3,0) -> 0
F27: 22 | G27: =sumif($C$6:$C65,F27,$D$6:$D65) -> 0 | H27: =H26-I27+G27 -> 67420 | I27: =sum(L27:AH27) -> 0 | K27: 22 | L27: =if((L3-L6-L7-L8-L9-L10-L11-L12-L13-L14-L15-L16-L17-L18-L19-L20-L21-L22-L23-L24-L25-L26)>0.1,L26,0) -> 0 | O27: 0 | P27: 0 | S27: 0 | T27: 0 | U27: 0 | V27: 0 | W27: 0 | AA27: =if($K27=$F$4,AA$3,0) -> 0 | AB27: =if($K27=$F$4,AB$3,0) -> 0 | AC27: =if($K27=$F$4,AC$3,0) -> 0 | AD27: =if($K27=$F$4,AD$3,0) -> 0 | AE27: =if($K27=$F$4,AE$3,0) -> 0 | AF27: =if($K27=$F$4,AF$3,0) -> 0 | AG27: =if($K27=$F$4,AG$3,0) -> 0 | AH27: =if($K27=$F$4,AH$3,0) -> 0
F28: 23 | G28: =sumif($C$6:$C66,F28,$D$6:$D66) -> 0 | H28: =H27-I28+G28 -> 67420 | I28: =sum(L28:AH28) -> 0 | K28: 23 | L28: =if((L3-L6-L7-L8-L9-L10-L11-L12-L13-L14-L15-L16-L17-L18-L19-L20-L21-L22-L23-L24-L25-L26-L27)>0.1,L27,0) -> 0 | O28: 0 | P28: 0 | S28: 0 | T28: 0 | U28: 0 | V28: 0 | W28: 0 | AA28: =if($K28=$F$4,AA$3,0) -> 0 | AB28: =if($K28=$F$4,AB$3,0) -> 0 | AC28: =if($K28=$F$4,AC$3,0) -> 0 | AD28: =if($K28=$F$4,AD$3,0) -> 0 | AE28: =if($K28=$F$4,AE$3,0) -> 0 | AF28: =if($K28=$F$4,AF$3,0) -> 0 | AG28: =if($K28=$F$4,AG$3,0) -> 0 | AH28: =if($K28=$F$4,AH$3,0) -> 0
F29: 24 | G29: =sumif($C$6:$C67,F29,$D$6:$D67) -> 0 | H29: =H28-I29+G29 -> 67420 | I29: =sum(L29:AH29) -> 0 | K29: 24 | L29: =if((L3-L6-L7-L8-L9-L10-L11-L12-L13-L14-L15-L16-L17-L18-L19-L20-L21-L22-L23-L24-L25-L26-L27-L28)>0.1,L28,0) -> 0 | O29: 0 | P29: 0 | S29: 0 | T29: 0 | U29: 0 | V29: 0 | W29: 0 | AA29: =if($K29=$F$4,AA$3,0) -> 0 | AB29: =if($K29=$F$4,AB$3,0) -> 0 | AC29: =if($K29=$F$4,AC$3,0) -> 0 | AD29: =if($K29=$F$4,AD$3,0) -> 0 | AE29: =if($K29=$F$4,AE$3,0) -> 0 | AF29: =if($K29=$F$4,AF$3,0) -> 0 | AG29: =if($K29=$F$4,AG$3,0) -> 0 | AH29: =if($K29=$F$4,AH$3,0) -> 0
F30: 25 | G30: =sumif($C$6:$C68,F30,$D$6:$D68) -> 0 | H30: =H29-I30+G30 -> 67420 | I30: =sum(L30:AH30) -> 0 | K30: 25 | L30: =if((L3-L6-L7-L8-L9-L10-L11-L12-L13-L14-L15-L16-L17-L18-L19-L20-L21-L22-L23-L24-L25-L26-L27-L28-L29)>0.1,L29,0) -> 0 | O30: =if((O3-O6-O10-O14-O18-O22-O26)>0.1,O26,0) -> 0 | P30: =if((P3-P6-P10-P14-P18-P22-P26)>0.1,P26,0) -> 0 | S30: =if((S3-S6-S10-S14-S18-S22-S26)>0.1,S26,0) -> 0 | T30: =if((T3-T6-T10-T14-T18-T22-T26)>0.1,T26,0) -> 0 | U30: =if((U3-U6-U10-U14-U18-U22-U26)>0.1,U26,0) -> 0 | V30: =if((V3-V6-V10-V14-V18-V22-V26)>0.1,V26,0) -> 0 | W30: =if((W3-W6-W10-W14-W18-W22-W26)>0.1,W26,0) -> 0 | AA30: =if($K30=$F$4,AA$3,0) -> 0 | AB30: =if($K30=$F$4,AB$3,0) -> 0 | AC30: =if($K30=$F$4,AC$3,0) -> 0 | AD30: =if($K30=$F$4,AD$3,0) -> 0 | AE30: =if($K30=$F$4,AE$3,0) -> 0 | AF30: =if($K30=$F$4,AF$3,0) -> 0 | AG30: =if($K30=$F$4,AG$3,0) -> 0 | AH30: =if($K30=$F$4,AH$3,0) -> 0
F31: 26 | G31: =sumif($C$6:$C69,F31,$D$6:$D69) -> 0 | H31: =H30-I31+G31 -> 67420 | I31: =sum(L31:AH31) -> 0 | K31: 26 | L31: =if((L3-L6-L7-L8-L9-L10-L11-L12-L13-L14-L15-L16-L17-L18-L19-L20-L21-L22-L23-L24-L25-L26-L27-L28-L29-L30)>0.1,L30,0) -> 0 | O31: 0 | P31: 0 | S31: 0 | T31: 0 | U31: 0 | V31: 0 | W31: 0 | AA31: =if($K31=$F$4,AA$3,0) -> 0 | AB31: =if($K31=$F$4,AB$3,0) -> 0 | AC31: =if($K31=$F$4,AC$3,0) -> 0 | AD31: =if($K31=$F$4,AD$3,0) -> 0 | AE31: =if($K31=$F$4,AE$3,0) -> 0 | AF31: =if($K31=$F$4,AF$3,0) -> 0 | AG31: =if($K31=$F$4,AG$3,0) -> 0 | AH31: =if($K31=$F$4,AH$3,0) -> 0
F32: 27 | G32: =sumif($C$6:$C70,F32,$D$6:$D70) -> 0 | H32: =H31-I32+G32 -> 67420 | I32: =sum(L32:AH32) -> 0 | K32: 27 | L32: =if((L3-L6-L7-L8-L9-L10-L11-L12-L13-L14-L15-L16-L17-L18-L19-L20-L21-L22-L23-L24-L25-L26-L27-L28-L29-L30-L31)>0.1,L31,0) -> 0 | O32: 0 | P32: 0 | S32: 0 | T32: 0 | U32: 0 | V32: 0 | W32: 0 | AA32: =if($K32=$F$4,AA$3,0) -> 0 | AB32: =if($K32=$F$4,AB$3,0) -> 0 | AC32: =if($K32=$F$4,AC$3,0) -> 0 | AD32: =if($K32=$F$4,AD$3,0) -> 0 | AE32: =if($K32=$F$4,AE$3,0) -> 0 | AF32: =if($K32=$F$4,AF$3,0) -> 0 | AG32: =if($K32=$F$4,AG$3,0) -> 0 | AH32: =if($K32=$F$4,AH$3,0) -> 0
F33: 28 | G33: =sumif($C$6:$C71,F33,$D$6:$D71) -> 0 | H33: =H32-I33+G33 -> 67420 | I33: =sum(L33:AH33) -> 0 | K33: 28 | L33: =if((L3-L6-L7-L8-L9-L10-L11-L12-L13-L14-L15-L16-L17-L18-L19-L20-L21-L22-L23-L24-L25-L26-L27-L28-L29-L30-L31-L32)>0.1,L32,0) -> 0 | O33: 0 | P33: 0 | S33: 0 | T33: 0 | U33: 0 | V33: 0 | W33: 0 | AA33: =if($K33=$F$4,AA$3,0) -> 0 | AB33: =if($K33=$F$4,AB$3,0) -> 0 | AC33: =if($K33=$F$4,AC$3,0) -> 0 | AD33: =if($K33=$F$4,AD$3,0) -> 0 | AE33: =if($K33=$F$4,AE$3,0) -> 0 | AF33: =if($K33=$F$4,AF$3,0) -> 0 | AG33: =if($K33=$F$4,AG$3,0) -> 0 | AH33: =if($K33=$F$4,AH$3,0) -> 0
F34: 29 | G34: =sumif($C$6:$C72,F34,$D$6:$D72) -> 0 | H34: =H33-I34+G34 -> 67420 | I34: =sum(L34:AH34) -> 0 | K34: 29 | L34: =if((L3-L6-L7-L8-L9-L10-L11-L12-L13-L14-L15-L16-L17-L18-L19-L20-L21-L22-L23-L24-L25-L26-L27-L28-L29-L30-L31-L32-L33)>0.1,L33,0) -> 0 | O34: =if((O3-O6-O10-O14-O18-O22-O26-O30)>0.1,O30,0) -> 0 | P34: =if((P3-P6-P10-P14-P18-P22-P26-P30)>0.1,P30,0) -> 0 | S34: =if((S3-S6-S10-S14-S18-S22-S26-S30)>0.1,S30,0) -> 0 | T34: =if((T3-T6-T10-T14-T18-T22-T26-T30)>0.1,T30,0) -> 0 | U34: =if((U3-U6-U10-U14-U18-U22-U26-U30)>0.1,U30,0) -> 0 | V34: =if((V3-V6-V10-V14-V18-V22-V26-V30)>0.1,V30,0) -> 0 | W34: =if((W3-W6-W10-W14-W18-W22-W26-W30)>0.1,W30,0) -> 0 | AA34: =if($K34=$F$4,AA$3,0) -> 0 | AB34: =if($K34=$F$4,AB$3,0) -> 0 | AC34: =if($K34=$F$4,AC$3,0) -> 0 | AD34: =if($K34=$F$4,AD$3,0) -> 0 | AE34: =if($K34=$F$4,AE$3,0) -> 0 | AF34: =if($K34=$F$4,AF$3,0) -> 0 | AG34: =if($K34=$F$4,AG$3,0) -> 0 | AH34: =if($K34=$F$4,AH$3,0) -> 0
F35: 30 | G35: =sumif($C$6:$C73,F35,$D$6:$D73) -> 0 | H35: =H34-I35+G35 -> 67420 | I35: =sum(L35:AH35) -> 0 | K35: 30 | L35: =if((L3-L6-L7-L8-L9-L10-L11-L12-L13-L14-L15-L16-L17-L18-L19-L20-L21-L22-L23-L24-L25-L26-L27-L28-L29-L30-L31-L32-L33-L34)>0.1,L34,0) -> 0 | O35: 0 | P35: 0 | S35: 0 | T35: 0 | U35: 0 | V35: 0 | W35: 0 | AA35: =if($K35=$F$4,AA$3,0) -> 0 | AB35: =if($K35=$F$4,AB$3,0) -> 0 | AC35: =if($K35=$F$4,AC$3,0) -> 0 | AD35: =if($K35=$F$4,AD$3,0) -> 0 | AE35: =if($K35=$F$4,AE$3,0) -> 0 | AF35: =if($K35=$F$4,AF$3,0) -> 0 | AG35: =if($K35=$F$4,AG$3,0) -> 0 | AH35: =if($K35=$F$4,AH$3,0) -> 0
F36: 31 | G36: =sumif($C$6:$C74,F36,$D$6:$D74) -> 0 | H36: =H35-I36+G36 -> 67420 | I36: =sum(L36:AH36) -> 0 | K36: 31 | L36: =if((L3-L6-L7-L8-L9-L10-L11-L12-L13-L14-L15-L16-L17-L18-L19-L20-L21-L22-L23-L24-L25-L26-L27-L28-L29-L30-L31-L32-L33-L34-L35)>0.1,L35,0) -> 0 | O36: 0 | P36: 0 | S36: 0 | T36: 0 | U36: 0 | V36: 0 | W36: 0 | AA36: =if($K36=$F$4,AA$3,0) -> 0 | AB36: =if($K36=$F$4,AB$3,0) -> 0 | AC36: =if($K36=$F$4,AC$3,0) -> 0 | AD36: =if($K36=$F$4,AD$3,0) -> 0 | AE36: =if($K36=$F$4,AE$3,0) -> 0 | AF36: =if($K36=$F$4,AF$3,0) -> 0 | AG36: =if($K36=$F$4,AG$3,0) -> 0 | AH36: =if($K36=$F$4,AH$3,0) -> 0
F37: 32 | G37: =sumif($C$6:$C75,F37,$D$6:$D75) -> 0 | H37: =H36-I37+G37 -> 67420 | I37: =sum(L37:AH37) -> 0 | K37: 32 | L37: =if((L3-L6-L7-L8-L9-L10-L11-L12-L13-L14-L15-L16-L17-L18-L19-L20-L21-L22-L23-L24-L25-L26-L27-L28-L29-L30-L31-L32-L33-L34-L35-L36)>0.1,L36,0) -> 0 | O37: 0 | P37: 0 | S37: 0 | T37: 0 | U37: 0 | V37: 0 | W37: 0 | AA37: =if($K37=$F$4,AA$3,0) -> 0 | AB37: =if($K37=$F$4,AB$3,0) -> 0 | AC37: =if($K37=$F$4,AC$3,0) -> 0 | AD37: =if($K37=$F$4,AD$3,0) -> 0 | AE37: =if($K37=$F$4,AE$3,0) -> 0 | AF37: =if($K37=$F$4,AF$3,0) -> 0 | AG37: =if($K37=$F$4,AG$3,0) -> 0 | AH37: =if($K37=$F$4,AH$3,0) -> 0
F38: 33 | G38: =sumif($C$6:$C76,F38,$D$6:$D76) -> 0 | H38: =H37-I38+G38 -> 67420 | I38: =sum(L38:AH38) -> 0 | K38: 33 | L38: =if((L3-L6-L7-L8-L9-L10-L11-L12-L13-L14-L15-L16-L17-L18-L19-L20-L21-L22-L23-L24-L25-L26-L27-L28-L29-L30-L31-L32-L33-L34-L35-L36-L37)>0.1,L37,0) -> 0 | O38: =if((O3-O6-O10-O14-O18-O22-O26-O30-O34)>0.1,O34,0) -> 0 | P38: =if((P3-P6-P10-P14-P18-P22-P26-P30-P34)>0.1,P34,0) -> 0 | S38: =if((S3-S6-S10-S14-S18-S22-S26-S30-S34)>0.1,S34,0) -> 0 | T38: =if((T3-T6-T10-T14-T18-T22-T26-T30-T34)>0.1,T34,0) -> 0 | U38: =if((U3-U6-U10-U14-U18-U22-U26-U30-U34)>0.1,U34,0) -> 0 | V38: =if((V3-V6-V10-V14-V18-V22-V26-V30-V34)>0.1,V34,0) -> 0 | W38: =if((W3-W6-W10-W14-W18-W22-W26-W30-W34)>0.1,W34,0) -> 0 | AA38: =if($K38=$F$4,AA$3,0) -> 0 | AB38: =if($K38=$F$4,AB$3,0) -> 0 | AC38: =if($K38=$F$4,AC$3,0) -> 0 | AD38: =if($K38=$F$4,AD$3,0) -> 0 | AE38: =if($K38=$F$4,AE$3,0) -> 0 | AF38: =if($K38=$F$4,AF$3,0) -> 0 | AG38: =if($K38=$F$4,AG$3,0) -> 0 | AH38: =if($K38=$F$4,AH$3,0) -> 0
F39: 34 | G39: =sumif($C$6:$C77,F39,$D$6:$D77) -> 0 | H39: =H38-I39+G39 -> 67420 | I39: =sum(L39:AH39) -> 0 | K39: 34 | L39: =if((L3-L6-L7-L8-L9-L10-L11-L12-L13-L14-L15-L16-L17-L18-L19-L20-L21-L22-L23-L24-L25-L26-L27-L28-L29-L30-L31-L32-L33-L34-L35-L36-L37-L38)>0.1,L38,0) -> 0 | O39: 0 | P39: 0 | S39: 0 | T39: 0 | U39: 0 | V39: 0 | W39: 0 | AA39: =if($K39=$F$4,AA$3,0) -> 0 | AB39: =if($K39=$F$4,AB$3,0) -> 0 | AC39: =if($K39=$F$4,AC$3,0) -> 0 | AD39: =if($K39=$F$4,AD$3,0) -> 0 | AE39: =if($K39=$F$4,AE$3,0) -> 0 | AF39: =if($K39=$F$4,AF$3,0) -> 0 | AG39: =if($K39=$F$4,AG$3,0) -> 0 | AH39: =if($K39=$F$4,AH$3,0) -> 0
F40: 35 | G40: =sumif($C$6:$C78,F40,$D$6:$D78) -> 0 | H40: =H39-I40+G40 -> 67420 | I40: =sum(L40:AH40) -> 0 | K40: 35 | L40: =if((L3-L6-L7-L8-L9-L10-L11-L12-L13-L14-L15-L16-L17-L18-L19-L20-L21-L22-L23-L24-L25-L26-L27-L28-L29-L30-L31-L32-L33-L34-L35-L36-L37-L38-L39)>0.1,L39,0) -> 0 | O40: 0 | P40: 0 | S40: 0 | T40: 0 | U40: 0 | V40: 0 | W40: 0 | AA40: =if($K40=$F$4,AA$3,0) -> 0 | AB40: =if($K40=$F$4,AB$3,0) -> 0 | AC40: =if($K40=$F$4,AC$3,0) -> 0 | AD40: =if($K40=$F$4,AD$3,0) -> 0 | AE40: =if($K40=$F$4,AE$3,0) -> 0 | AF40: =if($K40=$F$4,AF$3,0) -> 0 | AG40: =if($K40=$F$4,AG$3,0) -> 0 | AH40: =if($K40=$F$4,AH$3,0) -> 0
F41: 36 | G41: =sumif($C$6:$C79,F41,$D$6:$D79) -> 0 | H41: =H40-I41+G41 -> 67420 | I41: =sum(L41:AH41) -> 0 | K41: 36 | L41: =if((L3-L6-L7-L8-L9-L10-L11-L12-L13-L14-L15-L16-L17-L18-L19-L20-L21-L22-L23-L24-L25-L26-L27-L28-L29-L30-L31-L32-L33-L34-L35-L36-L37-L38-L39-L40)>0.1,L40,0) -> 0 | O41: 0 | P41: 0 | S41: 0 | T41: 0 | U41: 0 | V41: 0 | W41: 0 | AA41: =if($K41=$F$4,AA$3,0) -> 0 | AB41: =if($K41=$F$4,AB$3,0) -> 0 | AC41: =if($K41=$F$4,AC$3,0) -> 0 | AD41: =if($K41=$F$4,AD$3,0) -> 0 | AE41: =if($K41=$F$4,AE$3,0) -> 0 | AF41: =if($K41=$F$4,AF$3,0) -> 0 | AG41: =if($K41=$F$4,AG$3,0) -> 0 | AH41: =if($K41=$F$4,AH$3,0) -> 0
K42: TOTAL | L42: =sum(L6:L41) -> 20050 | M42: =sum(M6:M41) -> 200000 | N42: =sum(N6:N41) -> 6000 | O42: =sum(O6:O41) -> 0 | P42: =sum(P6:P41) -> 9333.3333 | Q42: =sum(Q6:Q41) -> 5833.3333 | R42: =sum(R6:R41) -> 0 | S42: =sum(S6:S41) -> 400 | ... AH42: =sum(AH6:AH41) -> 0
B43: Excess Cash Profit (Loss) ---> | E43: =H43-H3 -> 44453.333 | G43: Ending Bank Balance ---> | H43: {=INDEX(H6:H41,MATCH(143^143,H6:H41))} -> 67420 | K43: Unaccounted Costs --> | L43: =L3-L42 -> 0 | M43: =M3-M42 -> 0 | N43: =N3-N42 -> 0 | O43: =O3-O42 -> 0 | P43: =P3-P42 -> 0 | Q43: =Q3-Q42 -> 0 | R43: =R3-R42 -> 0 | S43: =S3-S42 -> 0 | ... AH43: =AH3-AH42 -> 0

Sheet Up Front Draw Cash Flow
A1: UP FRONT DRAW CASH FLOW SCHEDULE | K1: COSTS | L1: Construction Costs | M1: Purchase Price | N1: First Mortgage Points: | O1: First Mortgage Interest: | P1: First Mortgage Monthly Interest Only Payment: | Q1: Property Taxes | R1: HOA & Condo Fees | S1: Insurance Costs | T1: Utilities | X1: Buying Transaction Costs | AA1: Selling Transaction Costs | AF1: Staging Costs | AG1: Marketing Costs | AH1: Miscellaneous Selling Costs
A2: THE NUMBERS IN BLUE ARE AUTOMATICALLY CALCULATED. THE BOXES HIGHLIGHTED IN YELLOW ARE MEANT FOR YOU TO FILL OUT! | T2: Gas | U2: Water | V2: Electricity | W2: Miscellaneous | X2: Escrow / Attorney Fees | Y2: Title Insurance/Search Costs | Z2: Miscellaneous Buying Costs | AA2: Escrow / Attorney Fees | AB2: Selling Recording Fees | AC2: Realtor Fees | AD2: Transfer & Conveyance Fees | AE2: Home Warranty
B3: Net Cash In---> | C3: =sum(D6:D43) -> 300000 | F3: Duration Weeks | G3: Beginning Cash Balance ---> | H3: ='Aquisitions Deal Analyzer'!H39 -> 22966.667 | I3: Net Cash Out Below | K3: Estimated Total Costs | L3: ='Aquisitions Deal Analyzer'!E12 -> 20050 | M3: ='Aquisitions Deal Analyzer'!E11 -> 200000 | N3: ='Aquisitions Deal Analyzer'!F20 -> 6000 | O3: ='Aquisitions Deal Analyzer'!F21 -> 0 | P3: ='Aquisitions Deal Analyzer'!F22 -> 9333.3333 | Q3: ='Aquisitions Deal Analyzer'!K19 -> 5833.3333 | R3: ='Aquisitions Deal Analyzer'!K20 -> 0 | S3: ='Aquisitions Deal Analyzer'!K21 -> 400 | T3: ='Aquisitions Deal Analyzer'!K23 -> 600 | U3: ='Aquisitions Deal Analyzer'!K24 -> 400 | V3: ='Aquisitions Deal Analyzer'!K25 -> 400 | W3: ='Aquisitions Deal Analyzer'!K26 -> 0 | X3: ='Aquisitions Deal Analyzer'!F37 -> 1500 | Y3: ='Aquisitions Deal Analyzer'!F38 -> 3000 | Z3: ='Aquisitions Deal Analyzer'!F39 -> 0 | AA3: ='Aquisitions Deal Analyzer'!F42 -> 1500 | AB3: ='Aquisitions Deal Analyzer'!F43 -> 500 | AC3: ='Aquisitions Deal Analyzer'!F44 -> 6000 | AD3: ='Aquisitions Deal Analyzer'!F45 -> 30 | AE3: ='Aquisitions Deal Analyzer'!F46 -> 0 | AF3: ='Aquisitions Deal Analyzer'!F47 -> 0 | AG3: ='Aquisitions Deal Analyzer'!F48 -> 0 | AH3: ='Aquisitions Deal Analyzer'!F49 -> 0
F4: ='Aquisitions Deal Analyzer'!E9*4 -> 16 | I4: =sum(I6:I41) -> 255546.67 | K4: Frequency | L4: Weekly | M4: One Time | N4: One Time | O4: One Time | P4: Monthly | Q4: One Time | R4: One Time | S4: Monthly | T4: Monthly | U4: Monthly | V4: Monthly | W4: Monthly | X4: One Time | Y4: One Time | Z4: One Time | AA4: One Time | AB4: One Time | AC4: One Time | AD4: One Time | AE4: One Time | AF4: One Time | AG4: One Time | AH4: One Time
B5: Cash In Source | C5: Week | D5: Amount | F5: Week | G5: Cash In to the Project During this Week | H5: Balance @ End of Week | I5: Expenses Required | K5: Week
B6: Lender Purchase Loan | C6: 1 | D6: ='Aquisitions Deal Analyzer'!E11 -> 200000 | F6: 1 | G6: =sumif($C$6:$C44,F6,$D$6:$D44) -> 206683.33 | H6: =H4+H3-I6+G6 -> 9280.2083 | I6: =sum(L6:AH6) -> 220369.79 | K6: 1 | L6: =L3/(F4) -> 1253.125 | M6: =M3 -> 200000 | N6: =N3 -> 6000 | O6: =O3/('Aquisitions Deal Analyzer'!$E$9) -> 0 | P6: =P3/('Aquisitions Deal Analyzer'!$E$9) -> 2333.3333 | Q6: =Q3 -> 5833.3333 | R6: =R3 -> 0 | S6: =S3/('Aquisitions Deal Analyzer'!$E$9) -> 100 | T6: =T3/('Aquisitions Deal Analyzer'!$E$9) -> 150 | U6: =U3/('Aquisitions Deal Analyzer'!$E$9) -> 100 | V6: =V3/('Aquisitions Deal Analyzer'!$E$9) -> 100 | W6: =W3/('Aquisitions Deal Analyzer'!$E$9) -> 0 | X6: =X3 -> 1500 | Y6: =Y3 -> 3000 | Z6: =Z3 -> 0 | AA6: =if($K6=$F$4,AA$3,0) -> 0 | AB6: =if($K6=$F$4,AB$3,0) -> 0 | AC6: =if($K6=$F$4,AC$3,0) -> 0 | AD6: =if($K6=$F$4,AD$3,0) -> 0 | AE6: =if($K6=$F$4,AE$3,0) -> 0 | AF6: =if($K6=$F$4,AF$3,0) -> 0 | AG6: =if($K6=$F$4,AG$3,0) -> 0 | AH6: =if($K6=$F$4,AH$3,0) -> 0
B7: Lender Draw 1 at 1% | C7: =roundup($F$4*E7,0) -> 1 | D7: ='Aquisitions Deal Analyzer'!$E$12/3 -> 6683.3333 | E7: 0.01 | F7: 2 | G7: =sumif($C$6:$C45,F7,$D$6:$D45) -> 0 | H7: =H6-I7+G7 -> 8027.0833 | I7: =sum(L7:AH7) -> 1253.125 | K7: 2 | L7: =if((L3-L6)>0.1,L6,0) -> 1253.125 | O7: 0 | P7: 0 | S7: 0 | T7: 0 | U7: 0 | V7: 0 | W7: 0 | AA7: =if($K7=$F$4,AA$3,0) -> 0 | AB7: =if($K7=$F$4,AB$3,0) -> 0 | AC7: =if($K7=$F$4,AC$3,0) -> 0 | AD7: =if($K7=$F$4,AD$3,0) -> 0 | AE7: =if($K7=$F$4,AE$3,0) -> 0 | AF7: =if($K7=$F$4,AF$3,0) -> 0 | AG7: =if($K7=$F$4,AG$3,0) -> 0 | AH7: =if($K7=$F$4,AH$3,0) -> 0
B8: Lender Draw 2 at 33% | C8: =roundup($F$4*E8,0) -> 6 | D8: ='Aquisitions Deal Analyzer'!$E$12/3 -> 6683.3333 | E8: 0.33 | F8: 3 | G8: =sumif($C$6:$C46,F8,$D$6:$D46) -> 0 | H8: =H7-I8+G8 -> 6773.9583 | I8: =sum(L8:AH8) -> 1253.125 | K8: 3 | L8: =if((L3-L6-L7)>0.1,L7,0) -> 1253.125 | O8: 0 | P8: 0 | S8: 0 | T8: 0 | U8: 0 | V8: 0 | W8: 0 | AA8: =if($K8=$F$4,AA$3,0) -> 0 | AB8: =if($K8=$F$4,AB$3,0) -> 0 | AC8: =if($K8=$F$4,AC$3,0) -> 0 | AD8: =if($K8=$F$4,AD$3,0) -> 0 | AE8: =if($K8=$F$4,AE$3,0) -> 0 | AF8: =if($K8=$F$4,AF$3,0) -> 0 | AG8: =if($K8=$F$4,AG$3,0) -> 0 | AH8: =if($K8=$F$4,AH$3,0) -> 0
B9: Lender Draw 3 at 66% | C9: =roundup($F$4*E9,0) -> 11 | D9: ='Aquisitions Deal Analyzer'!$E$12/3 -> 6683.3333 | E9: 0.66 | F9: 4 | G9: =sumif($C$6:$C47,F9,$D$6:$D47) -> 0 | H9: =H8-I9+G9 -> 5520.8333 | I9: =sum(L9:AH9) -> 1253.125 | K9: 4 | L9: =if((L3-L6-L7-L8)>0.1,L8,0) -> 1253.125 | O9: 0 | P9: 0 | S9: 0 | T9: 0 | U9: 0 | V9: 0 | W9: 0 | AA9: =if($K9=$F$4,AA$3,0) -> 0 | AB9: =if($K9=$F$4,AB$3,0) -> 0 | AC9: =if($K9=$F$4,AC$3,0) -> 0 | AD9: =if($K9=$F$4,AD$3,0) -> 0 | AE9: =if($K9=$F$4,AE$3,0) -> 0 | AF9: =if($K9=$F$4,AF$3,0) -> 0 | AG9: =if($K9=$F$4,AG$3,0) -> 0 | AH9: =if($K9=$F$4,AH$3,0) -> 0
B10: Property Sale | C10: =F4 -> 16 | D10: ='Aquisitions Deal Analyzer'!E13 -> 300000 | F10: 5 | G10: =sumif($C$6:$C48,F10,$D$6:$D48) -> 0 | H10: =H9-I10+G10 -> 1484.375 | I10: =sum(L10:AH10) -> 4036.4583 | K10: 5 | L10: =if((L3-L6-L7-L8-L9)>0.1,L9,0) -> 1253.125 | O10: =if((O3-O6)>0.1,O6,0) -> 0 | P10: =if((P3-P6)>0.1,P6,0) -> 2333.3333 | S10: =if((S3-S6)>0.1,S6,0) -> 100 | T10: =if((T3-T6)>0.1,T6,0) -> 150 | U10: =if((U3-U6)>0.1,U6,0) -> 100 | V10: =if((V3-V6)>0.1,V6,0) -> 100 | W10: =if((W3-W6)>0.1,W6,0) -> 0 | AA10: =if($K10=$F$4,AA$3,0) -> 0 | AB10: =if($K10=$F$4,AB$3,0) -> 0 | AC10: =if($K10=$F$4,AC$3,0) -> 0 | AD10: =if($K10=$F$4,AD$3,0) -> 0 | AE10: =if($K10=$F$4,AE$3,0) -> 0 | AF10: =if($K10=$F$4,AF$3,0) -> 0 | AG10: =if($K10=$F$4,AG$3,0) -> 0 | AH10: =if($K10=$F$4,AH$3,0) -> 0
B11: Purchase Loan Repayment | C11: =F4 -> 16 | D11: =-'Aquisitions Deal Analyzer'!E11 -> -200000 | F11: 6 | G11: =sumif($C$6:$C49,F11,$D$6:$D49) -> 6683.3333 | H11: =H10-I11+G11 -> 6914.5833 | I11: =sum(L11:AH11) -> 1253.125 | K11: 6 | L11: =if((L3-L6-L7-L8-L9-L10)>0.1,L10,0) -> 1253.125 | O11: 0 | P11: 0 | S11: 0 | T11: 0 | U11: 0 | V11: 0 | W11: 0 | AA11: =if($K11=$F$4,AA$3,0) -> 0 | AB11: =if($K11=$F$4,AB$3,0) -> 0 | AC11: =if($K11=$F$4,AC$3,0) -> 0 | AD11: =if($K11=$F$4,AD$3,0) -> 0 | AE11: =if($K11=$F$4,AE$3,0) -> 0 | AF11: =if($K11=$F$4,AF$3,0) -> 0 | AG11: =if($K11=$F$4,AG$3,0) -> 0 | AH11: =if($K11=$F$4,AH$3,0) -> 0
B12: Construction Loan Repayment | C12: =F4 -> 16 | D12: =-'Aquisitions Deal Analyzer'!E12 -> -20050 | F12: 7 | G12: =sumif($C$6:$C50,F12,$D$6:$D50) -> 0 | H12: =H11-I12+G12 -> 5661.4583 | I12: =sum(L12:AH12) -> 1253.125 | K12: 7 | L12: =if((L3-L6-L7-L8-L9-L10-L11)>0.1,L11,0) -> 1253.125 | O12: 0 | P12: 0 | S12: 0 | T12: 0 | U12: 0 | V12: 0 | W12: 0 | AA12: =if($K12=$F$4,AA$3,0) -> 0 | AB12: =if($K12=$F$4,AB$3,0) -> 0 | AC12: =if($K12=$F$4,AC$3,0) -> 0 | AD12: =if($K12=$F$4,AD$3,0) -> 0 | AE12: =if($K12=$F$4,AE$3,0) -> 0 | AF12: =if($K12=$F$4,AF$3,0) -> 0 | AG12: =if($K12=$F$4,AG$3,0) -> 0 | AH12: =if($K12=$F$4,AH$3,0) -> 0
F13: 8 | G13: =sumif($C$6:$C51,F13,$D$6:$D51) -> 0 | H13: =H12-I13+G13 -> 4408.3333 | I13: =sum(L13:AH13) -> 1253.125 | K13: 8 | L13: =if((L3-L6-L7-L8-L9-L10-L11-L12)>0.1,L12,0) -> 1253.125 | O13: 0 | P13: 0 | S13: 0 | T13: 0 | U13: 0 | V13: 0 | W13: 0 | AA13: =if($K13=$F$4,AA$3,0) -> 0 | AB13: =if($K13=$F$4,AB$3,0) -> 0 | AC13: =if($K13=$F$4,AC$3,0) -> 0 | AD13: =if($K13=$F$4,AD$3,0) -> 0 | AE13: =if($K13=$F$4,AE$3,0) -> 0 | AF13: =if($K13=$F$4,AF$3,0) -> 0 | AG13: =if($K13=$F$4,AG$3,0) -> 0 | AH13: =if($K13=$F$4,AH$3,0) -> 0
B14: Other Expense 1 | F14: 9 | G14: =sumif($C$6:$C52,F14,$D$6:$D52) -> 0 | H14: =H13-I14+G14 -> 371.875 | I14: =sum(L14:AH14) -> 4036.4583 | K14: 9 | L14: =if((L3-L6-L7-L8-L9-L10-L11-L12-L13)>0.1,L13,0) -> 1253.125 | O14: =if((O3-O6-O10)>0.1,O10,0) -> 0 | P14: =if((P3-P6-P10)>0.1,P10,0) -> 2333.3333 | S14: =if((S3-S6-S10)>0.1,S10,0) -> 100 | T14: =if((T3-T6-T10)>0.1,T10,0) -> 150 | U14: =if((U3-U6-U10)>0.1,U10,0) -> 100 | V14: =if((V3-V6-V10)>0.1,V10,0) -> 100 | W14: =if((W3-W6-W10)>0.1,W10,0) -> 0 | AA14: =if($K14=$F$4,AA$3,0) -> 0 | AB14: =if($K14=$F$4,AB$3,0) -> 0 | AC14: =if($K14=$F$4,AC$3,0) -> 0 | AD14: =if($K14=$F$4,AD$3,0) -> 0 | AE14: =if($K14=$F$4,AE$3,0) -> 0 | AF14: =if($K14=$F$4,AF$3,0) -> 0 | AG14: =if($K14=$F$4,AG$3,0) -> 0 | AH14: =if($K14=$F$4,AH$3,0) -> 0
B15: Other Expense 2 | F15: 10 | G15: =sumif($C$6:$C53,F15,$D$6:$D53) -> 0 | H15: =H14-I15+G15 -> -881.25 | I15: =sum(L15:AH15) -> 1253.125 | K15: 10 | L15: =if((L3-L6-L7-L8-L9-L10-L11-L12-L13-L14)>0.1,L14,0) -> 1253.125 | O15: 0 | P15: 0 | S15: 0 | T15: 0 | U15: 0 | V15: 0 | W15: 0 | AA15: =if($K15=$F$4,AA$3,0) -> 0 | AB15: =if($K15=$F$4,AB$3,0) -> 0 | AC15: =if($K15=$F$4,AC$3,0) -> 0 | AD15: =if($K15=$F$4,AD$3,0) -> 0 | AE15: =if($K15=$F$4,AE$3,0) -> 0 | AF15: =if($K15=$F$4,AF$3,0) -> 0 | AG15: =if($K15=$F$4,AG$3,0) -> 0 | AH15: =if($K15=$F$4,AH$3,0) -> 0
B16: Other Expense 3 | F16: 11 | G16: =sumif($C$6:$C54,F16,$D$6:$D54) -> 6683.3333 | H16: =H15-I16+G16 -> 4548.9583 | I16: =sum(L16:AH16) -> 1253.125 | K16: 11 | L16: =if((L3-L6-L7-L8-L9-L10-L11-L12-L13-L14-15)>0.1,L15,0) -> 1253.125 | O16: 0 | P16: 0 | S16: 0 | T16: 0 | U16: 0 | V16: 0 | W16: 0 | AA16: =if($K16=$F$4,AA$3,0) -> 0 | AB16: =if($K16=$F$4,AB$3,0) -> 0 | AC16: =if($K16=$F$4,AC$3,0) -> 0 | AD16: =if($K16=$F$4,AD$3,0) -> 0 | AE16: =if($K16=$F$4,AE$3,0) -> 0 | AF16: =if($K16=$F$4,AF$3,0) -> 0 | AG16: =if($K16=$F$4,AG$3,0) -> 0 | AH16: =if($K16=$F$4,AH$3,0) -> 0
B17: Other Expense 4 | F17: 12 | G17: =sumif($C$6:$C55,F17,$D$6:$D55) -> 0 | H17: =H16-I17+G17 -> 3295.8333 | I17: =sum(L17:AH17) -> 1253.125 | K17: 12 | L17: =if((L3-L6-L7-L8-L9-L10-L11-L12-L13-L14-L15-L16)>0.1,L16,0) -> 1253.125 | O17: 0 | P17: 0 | S17: 0 | T17: 0 | U17: 0 | V17: 0 | W17: 0 | AA17: =if($K17=$F$4,AA$3,0) -> 0 | AB17: =if($K17=$F$4,AB$3,0) -> 0 | AC17: =if($K17=$F$4,AC$3,0) -> 0 | AD17: =if($K17=$F$4,AD$3,0) -> 0 | AE17: =if($K17=$F$4,AE$3,0) -> 0 | AF17: =if($K17=$F$4,AF$3,0) -> 0 | AG17: =if($K17=$F$4,AG$3,0) -> 0 | AH17: =if($K17=$F$4,AH$3,0) -> 0
B18: Other Expense 5 | F18: 13 | G18: =sumif($C$6:$C56,F18,$D$6:$D56) -> 0 | H18: =H17-I18+G18 -> -740.625 | I18: =sum(L18:AH18) -> 4036.4583 | K18: 13 | L18: =if((L3-L6-L7-L8-L9-L10-L11-L12-L13-L14-L15-L16-L17)>0.1,L17,0) -> 1253.125 | O18: =if((O3-O6-O10-O14)>0.1,O14,0) -> 0 | P18: =if((P3-P6-P10-P14)>0.1,P14,0) -> 2333.3333 | S18: =if((S3-S6-S10-S14)>0.1,S14,0) -> 100 | T18: =if((T3-T6-T10-T14)>0.1,T14,0) -> 150 | U18: =if((U3-U6-U10-U14)>0.1,U14,0) -> 100 | V18: =if((V3-V6-V10-V14)>0.1,V14,0) -> 100 | W18: =if((W3-W6-W10-W14)>0.1,W14,0) -> 0 | AA18: =if($K18=$F$4,AA$3,0) -> 0 | AB18: =if($K18=$F$4,AB$3,0) -> 0 | AC18: =if($K18=$F$4,AC$3,0) -> 0 | AD18: =if($K18=$F$4,AD$3,0) -> 0 | AE18: =if($K18=$F$4,AE$3,0) -> 0 | AF18: =if($K18=$F$4,AF$3,0) -> 0 | AG18: =if($K18=$F$4,AG$3,0) -> 0 | AH18: =if($K18=$F$4,AH$3,0) -> 0
F19: 14 | G19: =sumif($C$6:$C57,F19,$D$6:$D57) -> 0 | H19: =H18-I19+G19 -> -1993.75 | I19: =sum(L19:AH19) -> 1253.125 | K19: 14 | L19: =if((L3-L6-L7-L8-L9-L10-L11-L12-L13-L14-L15-L16-L17-L18)>0.1,L18,0) -> 1253.125 | O19: 0 | P19: 0 | S19: 0 | T19: 0 | U19: 0 | V19: 0 | W19: 0 | AA19: =if($K19=$F$4,AA$3,0) -> 0 | AB19: =if($K19=$F$4,AB$3,0) -> 0 | AC19: =if($K19=$F$4,AC$3,0) -> 0 | AD19: =if($K19=$F$4,AD$3,0) -> 0 | AE19: =if($K19=$F$4,AE$3,0) -> 0 | AF19: =if($K19=$F$4,AF$3,0) -> 0 | AG19: =if($K19=$F$4,AG$3,0) -> 0 | AH19: =if($K19=$F$4,AH$3,0) -> 0
F20: 15 | G20: =sumif($C$6:$C58,F20,$D$6:$D58) -> 0 | H20: =H19-I20+G20 -> -3246.875 | I20: =sum(L20:AH20) -> 1253.125 | K20: 15 | L20: =if((L3-L6-L7-L8-L9-L10-L11-L12-L13-L14-L15-L16-L17-L18-L19)>0.1,L19,0) -> 1253.125 | O20: 0 | P20: 0 | S20: 0 | T20: 0 | U20: 0 | V20: 0 | W20: 0 | AA20: =if($K20=$F$4,AA$3,0) -> 0 | AB20: =if($K20=$F$4,AB$3,0) -> 0 | AC20: =if($K20=$F$4,AC$3,0) -> 0 | AD20: =if($K20=$F$4,AD$3,0) -> 0 | AE20: =if($K20=$F$4,AE$3,0) -> 0 | AF20: =if($K20=$F$4,AF$3,0) -> 0 | AG20: =if($K20=$F$4,AG$3,0) -> 0 | AH20: =if($K20=$F$4,AH$3,0) -> 0
F21: 16 | G21: =sumif($C$6:$C59,F21,$D$6:$D59) -> 79950 | H21: =H20-I21+G21 -> 67420 | I21: =sum(L21:AH21) -> 9283.125 | K21: 16 | L21: =if((L3-L6-L7-L8-L9-L10-L11-L12-L13-L14-L15-L16-L17-L18-L19-L20)>0.1,L20,0) -> 1253.125 | O21: 0 | P21: 0 | S21: 0 | T21: 0 | U21: 0 | V21: 0 | W21: 0 | AA21: =if($K21=$F$4,AA$3,0) -> 1500 | AB21: =if($K21=$F$4,AB$3,0) -> 500 | AC21: =if($K21=$F$4,AC$3,0) -> 6000 | AD21: =if($K21=$F$4,AD$3,0) -> 30 | AE21: =if($K21=$F$4,AE$3,0) -> 0 | AF21: =if($K21=$F$4,AF$3,0) -> 0 | AG21: =if($K21=$F$4,AG$3,0) -> 0 | AH21: =if($K21=$F$4,AH$3,0) -> 0
F22: 17 | G22: =sumif($C$6:$C60,F22,$D$6:$D60) -> 0 | H22: =H21-I22+G22 -> 67420 | I22: =sum(L22:AH22) -> 0 | K22: 17 | L22: =if((L3-L6-L7-L8-L9-L10-L11-L12-L13-L14-L15-L16-L17-L18-L19-L20-L21)>0.1,L21,0) -> 0 | O22: =if((O3-O6-O10-O14-O18)>0.1,O18,0) -> 0 | P22: =if((P3-P6-P10-P14-P18)>0.1,P18,0) -> 0 | S22: =if((S3-S6-S10-S14-S18)>0.1,S18,0) -> 0 | T22: =if((T3-T6-T10-T14-T18)>0.1,T18,0) -> 0 | U22: =if((U3-U6-U10-U14-U18)>0.1,U18,0) -> 0 | V22: =if((V3-V6-V10-V14-V18)>0.1,V18,0) -> 0 | W22: =if((W3-W6-W10-W14-W18)>0.1,W18,0) -> 0 | AA22: =if($K22=$F$4,AA$3,0) -> 0 | AB22: =if($K22=$F$4,AB$3,0) -> 0 | AC22: =if($K22=$F$4,AC$3,0) -> 0 | AD22: =if($K22=$F$4,AD$3,0) -> 0 | AE22: =if($K22=$F$4,AE$3,0) -> 0 | AF22: =if($K22=$F$4,AF$3,0) -> 0 | AG22: =if($K22=$F$4,AG$3,0) -> 0 | AH22: =if($K22=$F$4,AH$3,0) -> 0
F23: 18 | G23: =sumif($C$6:$C61,F23,$D$6:$D61) -> 0 | H23: =H22-I23+G23 -> 67420 | I23: =sum(L23:AH23) -> 0 | K23: 18 | L23: =if((L3-L6-L7-L8-L9-L10-L11-L12-L13-L14-L15-L16-L17-L18-L19-L20-L21-L22)>0.1,L22,0) -> 0 | O23: 0 | P23: 0 | S23: 0 | T23: 0 | U23: 0 | V23: 0 | W23: 0 | AA23: =if($K23=$F$4,AA$3,0) -> 0 | AB23: =if($K23=$F$4,AB$3,0) -> 0 | AC23: =if($K23=$F$4,AC$3,0) -> 0 | AD23: =if($K23=$F$4,AD$3,0) -> 0 | AE23: =if($K23=$F$4,AE$3,0) -> 0 | AF23: =if($K23=$F$4,AF$3,0) -> 0 | AG23: =if($K23=$F$4,AG$3,0) -> 0 | AH23: =if($K23=$F$4,AH$3,0) -> 0
F24: 19 | G24: =sumif($C$6:$C62,F24,$D$6:$D62) -> 0 | H24: =H23-I24+G24 -> 67420 | I24: =sum(L24:AH24) -> 0 | K24: 19 | L24: =if((L3-L6-L7-L8-L9-L10-L11-L12-L13-L14-L15-L16-L17-L18-L19-L20-L21-L22-L23)>0.1,L23,0) -> 0 | O24: 0 | P24: 0 | S24: 0 | T24: 0 | U24: 0 | V24: 0 | W24: 0 | AA24: =if($K24=$F$4,AA$3,0) -> 0 | AB24: =if($K24=$F$4,AB$3,0) -> 0 | AC24: =if($K24=$F$4,AC$3,0) -> 0 | AD24: =if($K24=$F$4,AD$3,0) -> 0 | AE24: =if($K24=$F$4,AE$3,0) -> 0 | AF24: =if($K24=$F$4,AF$3,0) -> 0 | AG24: =if($K24=$F$4,AG$3,0) -> 0 | AH24: =if($K24=$F$4,AH$3,0) -> 0
F25: 20 | G25: =sumif($C$6:$C63,F25,$D$6:$D63) -> 0 | H25: =H24-I25+G25 -> 67420 | I25: =sum(L25:AH25) -> 0 | K25: 20 | L25: =if((L3-L6-L7-L8-L9-L10-L11-L12-L13-L14-L15-L16-L17-L18-L19-L20-L21-L22-L23-L24)>0.1,L24,0) -> 0 | O25: 0 | P25: 0 | S25: 0 | T25: 0 | U25: 0 | V25: 0 | W25: 0 | AA25: =if($K25=$F$4,AA$3,0) -> 0 | AB25: =if($K25=$F$4,AB$3,0) -> 0 | AC25: =if($K25=$F$4,AC$3,0) -> 0 | AD25: =if($K25=$F$4,AD$3,0) -> 0 | AE25: =if($K25=$F$4,AE$3,0) -> 0 | AF25: =if($K25=$F$4,AF$3,0) -> 0 | AG25: =if($K25=$F$4,AG$3,0) -> 0 | AH25: =if($K25=$F$4,AH$3,0) -> 0
F26: 21 | G26: =sumif($C$6:$C64,F26,$D$6:$D64) -> 0 | H26: =H25-I26+G26 -> 67420 | I26: =sum(L26:AH26) -> 0 | K26: 21 | L26: =if((L3-L6-L7-L8-L9-L10-L11-L12-L13-L14-L15-L16-L17-L18-L19-L20-L21-L22-L23-L24-L25)>0.1,L25,0) -> 0 | O26: =if((O3-O6-O10-O14-O18-O22)>0.1,O22,0) -> 0 | P26: =if((P3-P6-P10-P14-P18-P22)>0.1,P22,0) -> 0 | S26: =if((S3-S6-S10-S14-S18-S22)>0.1,S22,0) -> 0 | T26: =if((T3-T6-T10-T14-T18-T22)>0.1,T22,0) -> 0 | U26: =if((U3-U6-U10-U14-U18-U22)>0.1,U22,0) -> 0 | V26: =if((V3-V6-V10-V14-V18-V22)>0.1,V22,0) -> 0 | W26: =if((W3-W6-W10-W14-W18-W22)>0.1,W22,0) -> 0 | AA26: =if($K26=$F$4,AA$3,0) -> 0 | AB26: =if($K26=$F$4,AB$3,0) -> 0 | AC26: =if($K26=$F$4,AC$3,0) -> 0 | AD26: =if($K26=$F$4,AD$3,0) -> 0 | AE26: =if($K26=$F$4,AE$3,0) -> 0 | AF26: =if($K26=$F$4,AF$3,0) -> 0 | AG26: =if($K26=$F$4,AG$3,0) -> 0 | AH26: =if($K26=$F$4,AH$3,0) -> 0
F27: 22 | G27: =sumif($C$6:$C65,F27,$D$6:$D65) -> 0 | H27: =H26-I27+G27 -> 67420 | I27: =sum(L27:AH27) -> 0 | K27: 22 | L27: =if((L3-L6-L7-L8-L9-L10-L11-L12-L13-L14-L15-L16-L17-L18-L19-L20-L21-L22-L23-L24-L25-L26)>0.1,L26,0) -> 0 | O27: 0 | P27: 0 | S27: 0 | T27: 0 | U27: 0 | V27: 0 | W27: 0 | AA27: =if($K27=$F$4,AA$3,0) -> 0 | AB27: =if($K27=$F$4,AB$3,0) -> 0 | AC27: =if($K27=$F$4,AC$3,0) -> 0 | AD27: =if($K27=$F$4,AD$3,0) -> 0 | AE27: =if($K27=$F$4,AE$3,0) -> 0 | AF27: =if($K27=$F$4,AF$3,0) -> 0 | AG27: =if($K27=$F$4,AG$3,0) -> 0 | AH27: =if($K27=$F$4,AH$3,0) -> 0
F28: 23 | G28: =sumif($C$6:$C66,F28,$D$6:$D66) -> 0 | H28: =H27-I28+G28 -> 67420 | I28: =sum(L28:AH28) -> 0 | K28: 23 | L28: =if((L3-L6-L7-L8-L9-L10-L11-L12-L13-L14-L15-L16-L17-L18-L19-L20-L21-L22-L23-L24-L25-L26-L27)>0.1,L27,0) -> 0 | O28: 0 | P28: 0 | S28: 0 | T28: 0 | U28: 0 | V28: 0 | W28: 0 | AA28: =if($K28=$F$4,AA$3,0) -> 0 | AB28: =if($K28=$F$4,AB$3,0) -> 0 | AC28: =if($K28=$F$4,AC$3,0) -> 0 | AD28: =if($K28=$F$4,AD$3,0) -> 0 | AE28: =if($K28=$F$4,AE$3,0) -> 0 | AF28: =if($K28=$F$4,AF$3,0) -> 0 | AG28: =if($K28=$F$4,AG$3,0) -> 0 | AH28: =if($K28=$F$4,AH$3,0) -> 0
F29: 24 | G29: =sumif($C$6:$C67,F29,$D$6:$D67) -> 0 | H29: =H28-I29+G29 -> 67420 | I29: =sum(L29:AH29) -> 0 | K29: 24 | L29: =if((L3-L6-L7-L8-L9-L10-L11-L12-L13-L14-L15-L16-L17-L18-L19-L20-L21-L22-L23-L24-L25-L26-L27-L28)>0.1,L28,0) -> 0 | O29: 0 | P29: 0 | S29: 0 | T29: 0 | U29: 0 | V29: 0 | W29: 0 | AA29: =if($K29=$F$4,AA$3,0) -> 0 | AB29: =if($K29=$F$4,AB$3,0) -> 0 | AC29: =if($K29=$F$4,AC$3,0) -> 0 | AD29: =if($K29=$F$4,AD$3,0) -> 0 | AE29: =if($K29=$F$4,AE$3,0) -> 0 | AF29: =if($K29=$F$4,AF$3,0) -> 0 | AG29: =if($K29=$F$4,AG$3,0) -> 0 | AH29: =if($K29=$F$4,AH$3,0) -> 0
F30: 25 | G30: =sumif($C$6:$C68,F30,$D$6:$D68) -> 0 | H30: =H29-I30+G30 -> 67420 | I30: =sum(L30:AH30) -> 0 | K30: 25 | L30: =if((L3-L6-L7-L8-L9-L10-L11-L12-L13-L14-L15-L16-L17-L18-L19-L20-L21-L22-L23-L24-L25-L26-L27-L28-L29)>0.1,L29,0) -> 0 | O30: =if((O3-O6-O10-O14-O18-O22-O26)>0.1,O26,0) -> 0 | P30: =if((P3-P6-P10-P14-P18-P22-P26)>0.1,P26,0) -> 0 | S30: =if((S3-S6-S10-S14-S18-S22-S26)>0.1,S26,0) -> 0 | T30: =if((T3-T6-T10-T14-T18-T22-T26)>0.1,T26,0) -> 0 | U30: =if((U3-U6-U10-U14-U18-U22-U26)>0.1,U26,0) -> 0 | V30: =if((V3-V6-V10-V14-V18-V22-V26)>0.1,V26,0) -> 0 | W30: =if((W3-W6-W10-W14-W18-W22-W26)>0.1,W26,0) -> 0 | AA30: =if($K30=$F$4,AA$3,0) -> 0 | AB30: =if($K30=$F$4,AB$3,0) -> 0 | AC30: =if($K30=$F$4,AC$3,0) -> 0 | AD30: =if($K30=$F$4,AD$3,0) -> 0 | AE30: =if($K30=$F$4,AE$3,0) -> 0 | AF30: =if($K30=$F$4,AF$3,0) -> 0 | AG30: =if($K30=$F$4,AG$3,0) -> 0 | AH30: =if($K30=$F$4,AH$3,0) -> 0
F31: 26 | G31: =sumif($C$6:$C69,F31,$D$6:$D69) -> 0 | H31: =H30-I31+G31 -> 67420 | I31: =sum(L31:AH31) -> 0 | K31: 26 | L31: =if((L3-L6-L7-L8-L9-L10-L11-L12-L13-L14-L15-L16-L17-L18-L19-L20-L21-L22-L23-L24-L25-L26-L27-L28-L29-L30)>0.1,L30,0) -> 0 | O31: 0 | P31: 0 | S31: 0 | T31: 0 | U31: 0 | V31: 0 | W31: 0 | AA31: =if($K31=$F$4,AA$3,0) -> 0 | AB31: =if($K31=$F$4,AB$3,0) -> 0 | AC31: =if($K31=$F$4,AC$3,0) -> 0 | AD31: =if($K31=$F$4,AD$3,0) -> 0 | AE31: =if($K31=$F$4,AE$3,0) -> 0 | AF31: =if($K31=$F$4,AF$3,0) -> 0 | AG31: =if($K31=$F$4,AG$3,0) -> 0 | AH31: =if($K31=$F$4,AH$3,0) -> 0
F32: 27 | G32: =sumif($C$6:$C70,F32,$D$6:$D70) -> 0 | H32: =H31-I32+G32 -> 67420 | I32: =sum(L32:AH32) -> 0 | K32: 27 | L32: =if((L3-L6-L7-L8-L9-L10-L11-L12-L13-L14-L15-L16-L17-L18-L19-L20-L21-L22-L23-L24-L25-L26-L27-L28-L29-L30-L31)>0.1,L31,0) -> 0 | O32: 0 | P32: 0 | S32: 0 | T32: 0 | U32: 0 | V32: 0 | W32: 0 | AA32: =if($K32=$F$4,AA$3,0) -> 0 | AB32: =if($K32=$F$4,AB$3,0) -> 0 | AC32: =if($K32=$F$4,AC$3,0) -> 0 | AD32: =if($K32=$F$4,AD$3,0) -> 0 | AE32: =if($K32=$F$4,AE$3,0) -> 0 | AF32: =if($K32=$F$4,AF$3,0) -> 0 | AG32: =if($K32=$F$4,AG$3,0) -> 0 | AH32: =if($K32=$F$4,AH$3,0) -> 0
F33: 28 | G33: =sumif($C$6:$C71,F33,$D$6:$D71) -> 0 | H33: =H32-I33+G33 -> 67420 | I33: =sum(L33:AH33) -> 0 | K33: 28 | L33: =if((L3-L6-L7-L8-L9-L10-L11-L12-L13-L14-L15-L16-L17-L18-L19-L20-L21-L22-L23-L24-L25-L26-L27-L28-L29-L30-L31-L32)>0.1,L32,0) -> 0 | O33: 0 | P33: 0 | S33: 0 | T33: 0 | U33: 0 | V33: 0 | W33: 0 | AA33: =if($K33=$F$4,AA$3,0) -> 0 | AB33: =if($K33=$F$4,AB$3,0) -> 0 | AC33: =if($K33=$F$4,AC$3,0) -> 0 | AD33: =if($K33=$F$4,AD$3,0) -> 0 | AE33: =if($K33=$F$4,AE$3,0) -> 0 | AF33: =if($K33=$F$4,AF$3,0) -> 0 | AG33: =if($K33=$F$4,AG$3,0) -> 0 | AH33: =if($K33=$F$4,AH$3,0) -> 0
F34: 29 | G34: =sumif($C$6:$C72,F34,$D$6:$D72) -> 0 | H34: =H33-I34+G34 -> 67420 | I34: =sum(L34:AH34) -> 0 | K34: 29 | L34: =if((L3-L6-L7-L8-L9-L10-L11-L12-L13-L14-L15-L16-L17-L18-L19-L20-L21-L22-L23-L24-L25-L26-L27-L28-L29-L30-L31-L32-L33)>0.1,L33,0) -> 0 | O34: =if((O3-O6-O10-O14-O18-O22-O26-O30)>0.1,O30,0) -> 0 | P34: =if((P3-P6-P10-P14-P18-P22-P26-P30)>0.1,P30,0) -> 0 | S34: =if((S3-S6-S10-S14-S18-S22-S26-S30)>0.1,S30,0) -> 0 | T34: =if((T3-T6-T10-T14-T18-T22-T26-T30)>0.1,T30,0) -> 0 | U34: =if((U3-U6-U10-U14-U18-U22-U26-U30)>0.1,U30,0) -> 0 | V34: =if((V3-V6-V10-V14-V18-V22-V26-V30)>0.1,V30,0) -> 0 | W34: =if((W3-W6-W10-W14-W18-W22-W26-W30)>0.1,W30,0) -> 0 | AA34: =if($K34=$F$4,AA$3,0) -> 0 | AB34: =if($K34=$F$4,AB$3,0) -> 0 | AC34: =if($K34=$F$4,AC$3,0) -> 0 | AD34: =if($K34=$F$4,AD$3,0) -> 0 | AE34: =if($K34=$F$4,AE$3,0) -> 0 | AF34: =if($K34=$F$4,AF$3,0) -> 0 | AG34: =if($K34=$F$4,AG$3,0) -> 0 | AH34: =if($K34=$F$4,AH$3,0) -> 0
F35: 30 | G35: =sumif($C$6:$C73,F35,$D$6:$D73) -> 0 | H35: =H34-I35+G35 -> 67420 | I35: =sum(L35:AH35) -> 0 | K35: 30 | L35: =if((L3-L6-L7-L8-L9-L10-L11-L12-L13-L14-L15-L16-L17-L18-L19-L20-L21-L22-L23-L24-L25-L26-L27-L28-L29-L30-L31-L32-L33-L34)>0.1,L34,0) -> 0 | O35: 0 | P35: 0 | S35: 0 | T35: 0 | U35: 0 | V35: 0 | W35: 0 | AA35: =if($K35=$F$4,AA$3,0) -> 0 | AB35: =if($K35=$F$4,AB$3,0) -> 0 | AC35: =if($K35=$F$4,AC$3,0) -> 0 | AD35: =if($K35=$F$4,AD$3,0) -> 0 | AE35: =if($K35=$F$4,AE$3,0) -> 0 | AF35: =if($K35=$F$4,AF$3,0) -> 0 | AG35: =if($K35=$F$4,AG$3,0) -> 0 | AH35: =if($K35=$F$4,AH$3,0) -> 0
F36: 31 | G36: =sumif($C$6:$C74,F36,$D$6:$D74) -> 0 | H36: =H35-I36+G36 -> 67420 | I36: =sum(L36:AH36) -> 0 | K36: 31 | L36: =if((L3-L6-L7-L8-L9-L10-L11-L12-L13-L14-L15-L16-L17-L18-L19-L20-L21-L22-L23-L24-L25-L26-L27-L28-L29-L30-L31-L32-L33-L34-L35)>0.1,L35,0) -> 0 | O36: 0 | P36: 0 | S36: 0 | T36: 0 | U36: 0 | V36: 0 | W36: 0 | AA36: =if($K36=$F$4,AA$3,0) -> 0 | AB36: =if($K36=$F$4,AB$3,0) -> 0 | AC36: =if($K36=$F$4,AC$3,0) -> 0 | AD36: =if($K36=$F$4,AD$3,0) -> 0 | AE36: =if($K36=$F$4,AE$3,0) -> 0 | AF36: =if($K36=$F$4,AF$3,0) -> 0 | AG36: =if($K36=$F$4,AG$3,0) -> 0 | AH36: =if($K36=$F$4,AH$3,0) -> 0
F37: 32 | G37: =sumif($C$6:$C75,F37,$D$6:$D75) -> 0 | H37: =H36-I37+G37 -> 67420 | I37: =sum(L37:AH37) -> 0 | K37: 32 | L37: =if((L3-L6-L7-L8-L9-L10-L11-L12-L13-L14-L15-L16-L17-L18-L19-L20-L21-L22-L23-L24-L25-L26-L27-L28-L29-L30-L31-L32-L33-L34-L35-L36)>0.1,L36,0) -> 0 | O37: 0 | P37: 0 | S37: 0 | T37: 0 | U37: 0 | V37: 0 | W37: 0 | AA37: =if($K37=$F$4,AA$3,0) -> 0 | AB37: =if($K37=$F$4,AB$3,0) -> 0 | AC37: =if($K37=$F$4,AC$3,0) -> 0 | AD37: =if($K37=$F$4,AD$3,0) -> 0 | AE37: =if($K37=$F$4,AE$3,0) -> 0 | AF37: =if($K37=$F$4,AF$3,0) -> 0 | AG37: =if($K37=$F$4,AG$3,0) -> 0 | AH37: =if($K37=$F$4,AH$3,0) -> 0
F38: 33 | G38: =sumif($C$6:$C76,F38,$D$6:$D76) -> 0 | H38: =H37-I38+G38 -> 67420 | I38: =sum(L38:AH38) -> 0 | K38: 33 | L38: =if((L3-L6-L7-L8-L9-L10-L11-L12-L13-L14-L15-L16-L17-L18-L19-L20-L21-L22-L23-L24-L25-L26-L27-L28-L29-L30-L31-L32-L33-L34-L35-L36-L37)>0.1,L37,0) -> 0 | O38: =if((O3-O6-O10-O14-O18-O22-O26-O30-O34)>0.1,O34,0) -> 0 | P38: =if((P3-P6-P10-P14-P18-P22-P26-P30-P34)>0.1,P34,0) -> 0 | S38: =if((S3-S6-S10-S14-S18-S22-S26-S30-S34)>0.1,S34,0) -> 0 | T38: =if((T3-T6-T10-T14-T18-T22-T26-T30-T34)>0.1,T34,0) -> 0 | U38: =if((U3-U6-U10-U14-U18-U22-U26-U30-U34)>0.1,U34,0) -> 0 | V38: =if((V3-V6-V10-V14-V18-V22-V26-V30-V34)>0.1,V34,0) -> 0 | W38: =if((W3-W6-W10-W14-W18-W22-W26-W30-W34)>0.1,W34,0) -> 0 | AA38: =if($K38=$F$4,AA$3,0) -> 0 | AB38: =if($K38=$F$4,AB$3,0) -> 0 | AC38: =if($K38=$F$4,AC$3,0) -> 0 | AD38: =if($K38=$F$4,AD$3,0) -> 0 | AE38: =if($K38=$F$4,AE$3,0) -> 0 | AF38: =if($K38=$F$4,AF$3,0) -> 0 | AG38: =if($K38=$F$4,AG$3,0) -> 0 | AH38: =if($K38=$F$4,AH$3,0) -> 0
F39: 34 | G39: =sumif($C$6:$C77,F39,$D$6:$D77) -> 0 | H39: =H38-I39+G39 -> 67420 | I39: =sum(L39:AH39) -> 0 | K39: 34 | L39: =if((L3-L6-L7-L8-L9-L10-L11-L12-L13-L14-L15-L16-L17-L18-L19-L20-L21-L22-L23-L24-L25-L26-L27-L28-L29-L30-L31-L32-L33-L34-L35-L36-L37-L38)>0.1,L38,0) -> 0 | O39: 0 | P39: 0 | S39: 0 | T39: 0 | U39: 0 | V39: 0 | W39: 0 | AA39: =if($K39=$F$4,AA$3,0) -> 0 | AB39: =if($K39=$F$4,AB$3,0) -> 0 | AC39: =if($K39=$F$4,AC$3,0) -> 0 | AD39: =if($K39=$F$4,AD$3,0) -> 0 | AE39: =if($K39=$F$4,AE$3,0) -> 0 | AF39: =if($K39=$F$4,AF$3,0) -> 0 | AG39: =if($K39=$F$4,AG$3,0) -> 0 | AH39: =if($K39=$F$4,AH$3,0) -> 0
F40: 35 | G40: =sumif($C$6:$C78,F40,$D$6:$D78) -> 0 | H40: =H39-I40+G40 -> 67420 | I40: =sum(L40:AH40) -> 0 | K40: 35 | L40: =if((L3-L6-L7-L8-L9-L10-L11-L12-L13-L14-L15-L16-L17-L18-L19-L20-L21-L22-L23-L24-L25-L26-L27-L28-L29-L30-L31-L32-L33-L34-L35-L36-L37-L38-L39)>0.1,L39,0) -> 0 | O40: 0 | P40: 0 | S40: 0 | T40: 0 | U40: 0 | V40: 0 | W40: 0 | AA40: =if($K40=$F$4,AA$3,0) -> 0 | AB40: =if($K40=$F$4,AB$3,0) -> 0 | AC40: =if($K40=$F$4,AC$3,0) -> 0 | AD40: =if($K40=$F$4,AD$3,0) -> 0 | AE40: =if($K40=$F$4,AE$3,0) -> 0 | AF40: =if($K40=$F$4,AF$3,0) -> 0 | AG40: =if($K40=$F$4,AG$3,0) -> 0 | AH40: =if($K40=$F$4,AH$3,0) -> 0
F41: 36 | G41: =sumif($C$6:$C79,F41,$D$6:$D79) -> 0 | H41: =H40-I41+G41 -> 67420 | I41: =sum(L41:AH41) -> 0 | K41: 36 | L41: =if((L3-L6-L7-L8-L9-L10-L11-L12-L13-L14-L15-L16-L17-L18-L19-L20-L21-L22-L23-L24-L25-L26-L27-L28-L29-L30-L31-L32-L33-L34-L35-L36-L37-L38-L39-L40)>0.1,L40,0) -> 0 | O41: 0 | P41: 0 | S41: 0 | T41: 0 | U41: 0 | V41: 0 | W41: 0 | AA41: =if($K41=$F$4,AA$3,0) -> 0 | AB41: =if($K41=$F$4,AB$3,0) -> 0 | AC41: =if($K41=$F$4,AC$3,0) -> 0 | AD41: =if($K41=$F$4,AD$3,0) -> 0 | AE41: =if($K41=$F$4,AE$3,0) -> 0 | AF41: =if($K41=$F$4,AF$3,0) -> 0 | AG41: =if($K41=$F$4,AG$3,0) -> 0 | AH41: =if($K41=$F$4,AH$3,0) -> 0
K42: TOTAL | L42: =sum(L6:L41) -> 20050 | M42: =sum(M6:M41) -> 200000 | N42: =sum(N6:N41) -> 6000 | O42: =sum(O6:O41) -> 0 | P42: =sum(P6:P41) -> 9333.3333 | Q42: =sum(Q6:Q41) -> 5833.3333 | R42: =sum(R6:R41) -> 0 | S42: =sum(S6:S41) -> 400 | ... AH42: =sum(AH6:AH41) -> 0
B43: Excess Cash Profit (Loss) ---> | E43: =H43-H3 -> 44453.333 | G43: Ending Bank Balance ---> | H43: {=INDEX(H6:H41,MATCH(143^143,H6:H41))} -> 67420 | K43: Unaccounted Costs --> | L43: =L3-L42 -> 0 | M43: =M3-M42 -> 0 | N43: =N3-N42 -> 0 | O43: =O3-O42 -> 0 | P43: =P3-P42 -> 0 | Q43: =Q3-Q42 -> 0 | R43: =R3-R42 -> 0 | S43: =S3-S42 -> 0 | ... AH43: =AH3-AH42 -> 0

Sheet Buy & Hold
B2: Easy Enough: Just fill in all the blue cells while reviewing a property and the results will populate throughout the sheet!
Y4: Rent Growth Calculator
B5: Sale Price | C5: 210000 | E5: Tax Value | F5: 210000 | H5: Current Pro Forma Analysis | N5: 5 Year Debt Paydown Summary | R5: Does it qualify for a commercial loan? | Y5: Rent Growth Rate: | Z5: 0.035
H6: CUURENT RATE ANALYSIS | R6: Debt Coverage Ratio Required: | T6: 1.25 | Y6: Market Rent (Year 1): | Z6: =F29 -> 3000
B7: Unit Breakdown | H7: Item | I7: $/Mo. | K7: Mortgage Calculator | O7: Year | P7: Figure
B8: Unit # | C8: #Beds | D8: #Baths | E8: Rent/Mo | F8: Market Rent | H8: Gross Rents | I8: =E29 -> 2000 | K8: Sale Price | L8: =C5 -> 210000 | N8: Total Debt Paydown | O8: 1 | P8: =($L$15*12)-P26 -> 2111.8686 | T8: Assumption | U8: Pro Forma | V8: Actual | Y8: End of Year: | Z8: Market Rent
B9: 1 | C9: 3 | D9: 2.5 | E9: 2000 | F9: 3000 | H9: Property Management | I9: =C$40*I8 -> 0 | K9: Loan to Value Ratio | L9: =1-E$33 -> 0.99 | N9: ROI on Paydown | O9: 1 | P9: =((P8)/$L$10) -> 1.0056517 | R9: Gross Rents | U9: =I8*12 -> 24000 | V9: =I23*12 -> 36000 | Y9: 1 | Z9: =Z$6*((1+Z$5)^(Y9-1)) -> 3000
B10: 2 | C10: 3 | D10: 3 | E10: 0 | F10: 0 | H10: Property Taxes | I10: =C$33/12 -> 116.66667 | K10: Down Payment | L10: =E33*C5 -> 2100 | N10: Total Debt Paydown | O10: 2 | P10: =($L$15*12)-P29 -> 2264.5358 | R10: Vacancy | T10: =C41 -> 0 | U10: =U9*T10 -> 0 | V10: =I13*12 -> 0 | Y10: 2 | Z10: =Z$6*((1+Z$5)^(Y10-1)) -> 3105
B11: 3 | C11: 3 | D11: 3 | E11: 0 | F11: 0 | H11: Insurance | I11: =C34 -> 100 | K11: Closing Costs | L11: =E$36 -> 2100 | N11: ROI on Paydown | O11: 2 | P11: =((P10)/$L$10) -> 1.0783504 | R11: Prop Mgmt | T11: =C40 -> 0 | U11: =U9*T11 -> 0 | V11: =12*I9 -> 0 | Y11: 3 | Z11: =Z$6*((1+Z$5)^(Y11-1)) -> 3213.675
B12: 4 | C12: 3 | D12: 3 | E12: 0 | F12: 0 | H12: Owner-Paid Utilities | I12: =SUM(C$35:C$39) -> 0 | K12: Principal | L12: =L8*L9 -> 207900 | N12: Total Debt Paydown | O12: 3 | P12: =($L$15*12)-P32 -> 2428.2393 | R12: Cash Reserves | T12: 0 | U12: =T12*U9 -> 0 | V12: =T12*V9 -> 0 | Y12: 4 | Z12: =Z$6*((1+Z$5)^(Y12-1)) -> 3326.1536
B13: 5 | C13: 3 | D13: 3 | E13: 0 | F13: 0 | H13: Vacancy Reserve | I13: =C41*E29 -> 0 | K13: Interest Rate | L13: =E$34 -> 0.07 | N13: ROI on Paydown | O13: 3 | P13: =((P12)/$L$10) -> 1.1563044 | R13: Taxes (actual) | U13: =I10*12 -> 1400 | V13: =I10*12 -> 1400 | Y13: 5 | Z13: =Z$6*((1+Z$5)^(Y13-1)) -> 3442.569
B14: 6 | C14: 3 | D14: 3 | E14: 0 | F14: 0 | H14: Maintenance Reserve | I14: =I$8*C42 -> 100 | K14: Term (Years) | L14: =E$35 -> 30 | N14: Total Debt Paydown | O14: 4 | P14: =($L$15*12)-P35 -> 2603.7769 | R14: Insurance (actual) | U14: =I11*12 -> 1200 | V14: =I11*12 -> 1200 | Y14: 6 | Z14: =Z$6*((1+Z$5)^(Y14-1)) -> 3563.0589
B15: 7 | C15: 3 | D15: 3 | E15: 0 | F15: 0 | H15: Total Operating Expenses | I15: =SUM(I9:I14) -> 316.66667 | K15: Monthly Mortgage | L15: =-pmt(L13/12,L14*12, L12) -> 1383.1639 | N15: ROI on Paydown | O15: 4 | P15: =((P14)/$L$10) -> 1.2398938 | R15: Maintenance + Utilities | T15: =C42 -> 0.05 | U15: =U9*T15 -> 1200 | V15: =(I12+I14)*12 -> 1200 | Y15: 7 | Z15: =Z$6*((1+Z$5)^(Y15-1)) -> 3687.766
B16: 8 | C16: 3 | D16: 3 | E16: 0 | F16: 0 | H16: Monthly NOI | I16: =I8-SUM(I9:I14) -> 1683.3333 | K16: Monthly Net | L16: =I16-L15 -> 300.16945 | N16: Total Debt Paydown | O16: 5 | P16: =($L$15*12)-P38 -> 2792.0041 | R16: Total Expenses | U16: =SUM(U10:U14,U15) -> 3800 | V16: =SUM(V10:V14,V15) -> 3800 | Y16: 8 | Z16: =Z$6*((1+Z$5)^(Y16-1)) -> 3816.8378
B17: 9 | C17: 3 | D17: 2.5 | E17: 0 | F17: 0 | H17: Annualized NOI | I17: =I16*12 -> 20200 | K17: Annualized Net | L17: =L16*12 -> 3602.0334 | N17: ROI on Paydown | O17: 5 | P17: =((P16)/$L$10) -> 1.3295258 | R17: NOI | U17: =U9-U16 -> 20200 | V17: =V9-V16 -> 32200 | Y17: 9 | Z17: =Z$6*((1+Z$5)^(Y17-1)) -> 3950.4271
B18: 10 | C18: 3 | D18: 2.5 | E18: 0 | F18: 0 | H18: Capitalization Rate | I18: =I17/L8 -> 0.096190476 | K18: Annualized ROI | L18: =L17/(L10+L11) -> 0.85762699 | R18: Mortgage | U18: =L15*12 -> 16597.967 | V18: =U18 -> 16597.967 | Y18: 10 | Z18: =Z$6*((1+Z$5)^(Y18-1)) -> 4088.6921
B19: 11 | C19: 3 | D19: 2.5 | E19: 0 | F19: 0 | Y19: 11 | Z19: =Z$6*((1+Z$5)^(Y19-1)) -> 4231.7963
B20: 12 | C20: 3 | D20: 2.5 | E20: 0 | F20: 0 | H20: Stabilized pro forma analysis | N20: Five Year Tax Deduction Summary | R20: Debt Coverage Ratio | U20: =U17/U18 -> 1.2170165 | V20: =V17/V18 -> 1.9399967 | Y20: 12 | Z20: =Z$6*((1+Z$5)^(Y20-1)) -> 4379.9092
B21: 13 | C21: 3 | D21: 2.5 | E21: 0 | F21: 0 | H21: MARKET RATE ANALYSIS | N21: Improved Value: Assessed Value Ratio (%) | P21: 1 | R21: Net Profit | U21: =U17-U18 -> 3602.0334 | V21: =V17-V18 -> 15602.033 | Y21: 13 | Z21: =Z$6*((1+Z$5)^(Y21-1)) -> 4533.206
B22: 14 | C22: 3 | D22: 2.5 | E22: 0 | F22: 0 | H22: Item | I22: $/Mo. | K22: Mortgage Calculator | N22: Marginal Tax Rate | P22: 0.21 | Y22: 14 | Z22: =Z$6*((1+Z$5)^(Y22-1)) -> 4691.8682
B23: 15 | F23: 0 | H23: Gross Rents | I23: =F29 -> 3000 | K23: Sale Price | L23: =C5 -> 210000 | R23: Average Annualized % Appreciation | Y23: 15 | Z23: =Z$6*((1+Z$5)^(Y23-1)) -> 4856.0836
B24: 16 | H24: Property Management | I24: =C$40*I23 -> 0 | K24: Loan to Value Ratio | L24: =1-E$33 -> 0.99 | O24: Year | P24: Figure | R24: Assumed Rate: | S24: 0.025 | Y24: 16 | Z24: =Z$6*((1+Z$5)^(Y24-1)) -> 5026.0465
B25: 17 | H25: Property Taxes | I25: =C$33/12 -> 116.66667 | K25: Down Payment | L25: =E33*L23 -> 2100 | N25: Depreciation (Straight Line) | O25: 1 | P25: =(P21*$L$8)/27.5 -> 7636.3636 | Y25: 17 | Z25: =Z$6*((1+Z$5)^(Y25-1)) -> 5201.9581
B26: 18 | H26: Insurance | I26: =C$34 -> 100 | K26: Closing Costs | L26: =E$36 -> 2100 | N26: Total Interest Paid | O26: 1 | P26: =-CUMIPMT($L$13/12,$L$14*12,$L$12,(1+(12*(O26-1))),(12*O26),0) -> 14486.098 | R26: End of Year: | S26: Est. Value | T26: Annual Gain | U26: % Gain | Y26: 18 | Z26: =Z$6*((1+Z$5)^(Y26-1)) -> 5384.0267
B27: 19 | H27: Owner-Paid Utilities | I27: =SUM(C$35:C$39) -> 0 | K27: Principal | L27: =L23*L24 -> 207900 | N27: Total Deductions | O27: 1 | P27: =SUM($P$25+$P26) -> 22122.462 | R27: 1 | S27: =L8+(L8*$S$24) -> 215250 | T27: =S27-L8 -> 5250 | U27: =T27/$L$10 -> 2.5 | Y27: 19 | Z27: =Z$6*((1+Z$5)^(Y27-1)) -> 5572.4676
B28: 20 | H28: Vacancy Reserve | I28: =C$41*I23 -> 0 | K28: Interest Rate | L28: =E$34 -> 0.07 | N28: Depreciation (Straight Line) | O28: 2 | P28: =(P21*$L$8)/27.5 -> 7636.3636 | R28: 2 | S28: =S27+(S27*$S$24) -> 220631.25 | T28: =S28-S27 -> 5381.25 | U28: =T28/$L$10 -> 2.5625 | Y28: 20 | Z28: =Z$6*((1+Z$5)^(Y28-1)) -> 5767.504
B29: Totals | E29: =SUM(E9:E28) -> 2000 | F29: =SUM(F9:F28) -> 3000 | H29: Maintenance Reserve | I29: =C42*I23 -> 150 | K29: Term (Years) | L29: =E$35 -> 30 | N29: Total Interest Paid | O29: 2 | P29: =-CUMIPMT($L$13/12,$L$14*12,$L$12,(1+(12*(O29-1))),(12*O29),0) -> 14333.431 | R29: 3 | S29: =S28+(S28*$S$24) -> 226147.03 | T29: =S29-S28 -> 5515.7812 | U29: =T29/$L$10 -> 2.6265625
H30: Total Operating Expenses | I30: =SUM(I24:I29) -> 366.66667 | K30: Monthly Mortgage | L30: =-pmt(L28/12,L29*12, L27) -> 1383.1639 | N30: Total Deductions | O30: 2 | P30: =SUM($P$25+$P29) -> 21969.794 | R30: 4 | S30: =S29+(S29*$S$24) -> 231800.71 | T30: =S30-S29 -> 5653.6758 | U30: =T30/$L$10 -> 2.6922266
B31: Expenses | D31: Mortgage | H31: Monthly NOI | I31: =I23-I30 -> 2633.3333 | K31: Monthly Net | L31: =I31-L30 -> 1250.1694 | N31: Depreciation (Straight Line) | O31: 3 | P31: =(P21*$L$8)/27.5 -> 7636.3636 | R31: 5 | S31: =S30+(S30*$S$24) -> 237595.72 | T31: =S31-S30 -> 5795.0177 | U31: =T31/$L$10 -> 2.7595322
H32: Annualized NOI | I32: =I31*12 -> 31600 | K32: Annualized Net | L32: =L31*12 -> 15002.033 | N32: Total Interest Paid | O32: 3 | P32: =-CUMIPMT($L$13/12,$L$14*12,$L$12,(1+(12*(O32-1))),(12*O32),0) -> 14169.727
B33: Property Tax/Yr | C33: 1400 | D33: Downpayment (%) | E33: 0.01 | F33: Discount | H33: Capitalization Rate | I33: =I32/L23 -> 0.15047619 | K33: Annualized ROI | L33: =L32/(L25+L26) -> 3.5719127 | N33: Total Deductions | O33: 3 | P33: =SUM($P$25+$P32) -> 21806.091 | R33: Total Return (% of initial investment)
B34: Insurance/Mo | C34: 100 | D34: Interest Rate (%) | E34: 0.07 | N34: Depreciation (Straight Line) | O34: 4 | P34: =(P21*$L$8)/27.5 -> 7636.3636 | R34: Year | S34: 1 | T34: 2 | U34: 3 | V34: 4 | W34: 5
B35: Gas & Electric/Mo | C35: 0 | D35: Loan Term (Years) | E35: 30 | N35: Total Interest Paid | O35: 4 | P35: =-CUMIPMT($L$13/12,$L$14*12,$L$12,(1+(12*(O35-1))),(12*O35),0) -> 13994.19 | R35: Source of Gain
B36: Water/Mo | C36: 0 | D36: Closing Costs | E36: =0.01*C5 -> 2100 | F36: Estimated 1% for closing | N36: Total Deductions | O36: 4 | P36: =SUM($P$25+$P35) -> 21630.553 | R36: Cash flow | S36: =$L$33 -> 3.5719127 | T36: =$L$33 -> 3.5719127 | U36: =$L$33 -> 3.5719127 | V36: =$L$33 -> 3.5719127 | W36: =$L$33 -> 3.5719127
B37: Sewer/Mo | C37: 0 | N37: Depreciation (Straight Line) | O37: 5 | P37: =(P21*$L$8)/27.5 -> 7636.3636 | R37: Debt Paydown | S37: =P9 -> 1.0056517 | T37: =P11 -> 1.0783504 | U37: =P13 -> 1.1563044 | V37: =P15 -> 1.2398938 | W37: =P17 -> 1.3295258
B38: Garbage/Mo | C38: 0 | N38: Total Interest Paid | O38: 5 | P38: =-CUMIPMT($L$13/12,$L$14*12,$L$12,(1+(12*(O38-1))),(12*O38),0) -> 13805.963 | R38: Tax Savings | S38: =(P27*P22)/L10 -> 2.2122462 | T38: =(P30*P22)/L10 -> 2.1969795 | U38: =(P33*P22)/L10 -> 2.1806091 | V38: =(P36*P22)/L10 -> 2.1630553 | W38: =(P39*P22)/L10 -> 2.1442326
B39: Lawn and Snow | C39: 0 | N39: Total Deductions | O39: 5 | P39: =SUM($P$25+$P38) -> 21442.326 | R39: Appreciation | S39: =U27 -> 2.5 | T39: =U28 -> 2.5625 | U39: =U29 -> 2.6265625 | V39: =U30 -> 2.6922266 | W39: =U31 -> 2.7595322
B40: Management (%) | C40: 0 | N40: Avg Yearly Tax Savings | P40: =(AVERAGE(P27,P30,P33,P36,P39))*P22 -> 4576.7915 | R40: Total ROI | S40: =SUM(S36:S39) -> 9.2898106 | T40: =SUM(T36:T39) -> 9.4097425 | U40: =SUM(U36:U39) -> 9.5353887 | V40: =SUM(V36:V39) -> 9.6670884 | W40: =SUM(W36:W39) -> 9.8052033
B41: Vacancy (%) | C41: 0 | N41: % Annual ROI on Tax Savings | P41: =P40/L10 -> 2.1794245 | R41: Total $ Return | S41: =S40*$L$10 -> 19508.602 | T41: =T40*$L$10 -> 19760.459 | U41: =U40*$L$10 -> 20024.316 | V41: =V40*$L$10 -> 20300.886 | W41: =W40*$L$10 -> 20590.927
B42: Maintenance (%) | C42: 0.05

Sheet Buy & Hold 2
B2: Easy Enough: Just fill in all the blue cells while reviewing a property and the results will populate throughout the sheet!
Y4: Rent Growth Calculator
B5: Sale Price | C5: 1500000 | E5: Tax Value | F5: 1500000 | H5: Current Pro Forma Analysis | N5: 5 Year Debt Paydown Summary | R5: Does it qualify for a commercial loan? | Y5: Rent Growth Rate: | Z5: 0.035
E6: =E9/0.4 -> 33500 | F6: =E6*12 -> 402000 | R6: Debt Coverage Ratio Required: | T6: 1.25 | Y6: Market Rent (Year 1): | Z6: =F29 -> 13400
B7: Unit Breakdown | H7: Item | I7: $/Mo. | K7: Mortgage Calculator | O7: Year | P7: Figure
B8: Unit # | C8: #Beds | D8: #Baths | E8: Rent/Mo | F8: Market Rent | H8: Gross Rents | I8: =E29 -> 13400 | K8: Sale Price | L8: =C5 -> 1500000 | N8: Total Debt Paydown | O8: 1 | P8: =($L$15*12)-P26 -> 10205.494 | T8: Assumption | U8: Pro Forma | V8: Actual | Y8: End of Year: | Z8: Market Rent
B9: 1 | C9: 3.5 | D9: 3 | E9: 13400 | F9: 13400 | H9: Property Management | I9: =C$40*I8 -> 0 | K9: Loan to Value Ratio | L9: =1-E$33 -> 0.9 | N9: ROI on Paydown | O9: 1 | P9: =((P8)/$L$10) -> 0.068036625 | R9: Gross Rents | U9: =I8*12 -> 160800 | V9: =I8*12 -> 160800 | Y9: 1 | Z9: =Z$6*((1+Z$5)^(Y9-1)) -> 13400
B10: 2 | H10: Property Taxes | I10: =C$33/12 -> 787.5 | K10: Down Payment | L10: =E33*C5 -> 150000 | N10: Total Debt Paydown | O10: 2 | P10: =($L$15*12)-P29 -> 11107.567 | R10: Vacancy | T10: 0.1 | U10: =U9*T10 -> 16080 | V10: =I13*12 -> 0 | Y10: 2 | Z10: =Z$6*((1+Z$5)^(Y10-1)) -> 13869
B11: 3 | H11: Insurance | I11: =C34 -> 32 | K11: Closing Costs | L11: =E$36 -> 45000 | N11: ROI on Paydown | O11: 2 | P11: =((P10)/$L$10) -> 0.074050444 | R11: Prop Mgmt | T11: 0.08 | U11: =U9*T11 -> 12864 | V11: =12*I9 -> 0 | Y11: 3 | Z11: =Z$6*((1+Z$5)^(Y11-1)) -> 14354.415
B12: 4 | H12: Owner-Paid Utilities | I12: =SUM(C$35:C$39) -> 1500 | K12: Principal | L12: =L8*L9 -> 1350000 | N12: Total Debt Paydown | O12: 3 | P12: =($L$15*12)-P32 -> 12089.374 | R12: Cash Reserves | T12: 0.03 | U12: =T12*U9 -> 4824 | V12: =0.03*V9 -> 4824 | Y12: 4 | Z12: =Z$6*((1+Z$5)^(Y12-1)) -> 14856.82
B13: 5 | H13: Vacancy Reserve | I13: =C41*E29 -> 0 | K13: Interest Rate | L13: =E$34 -> 0.085 | N13: ROI on Paydown | O13: 3 | P13: =((P12)/$L$10) -> 0.08059583 | R13: Taxes (actual) | U13: =I10*12 -> 9450 | V13: =I10*12 -> 9450 | Y13: 5 | Z13: =Z$6*((1+Z$5)^(Y13-1)) -> 15376.808
B14: 6 | H14: Maintenance Reserve | I14: =I$8*C42 -> 670 | K14: Term (Years) | L14: =E$35 -> 30 | N14: Total Debt Paydown | O14: 4 | P14: =($L$15*12)-P35 -> 13157.965 | R14: Insurance (actual) | U14: =I11*12 -> 384 | V14: =I11*12 -> 384 | Y14: 6 | Z14: =Z$6*((1+Z$5)^(Y14-1)) -> 15914.996
B15: 7 | H15: Total Operating Expenses | I15: =SUM(I9:I14) -> 2989.5 | K15: Monthly Mortgage | L15: =-pmt(L13/12,L14*12, L12) -> 10380.332 | N15: ROI on Paydown | O15: 4 | P15: =((P14)/$L$10) -> 0.087719768 | R15: Maintenance + Utilities | T15: 0.2 | U15: =U9*T15 -> 32160 | V15: =(I12+I14)*12 -> 26040 | Y15: 7 | Z15: =Z$6*((1+Z$5)^(Y15-1)) -> 16472.021
B16: 8 | H16: Monthly NOI | I16: =I8-SUM(I9:I14) -> 10410.5 | K16: Monthly Net | L16: =I16-L15 -> 30.167972 | N16: Total Debt Paydown | O16: 5 | P16: =($L$15*12)-P38 -> 14321.01 | R16: Total Expenses | U16: =SUM(U10:U14,U15) -> 75762 | V16: =SUM(V10:V14,V15) -> 40698 | Y16: 8 | Z16: =Z$6*((1+Z$5)^(Y16-1)) -> 17048.542
B17: 9 | H17: Annualized NOI | I17: =I16*12 -> 124926 | K17: Annualized Net | L17: =L16*12 -> 362.01566 | N17: ROI on Paydown | O17: 5 | P17: =((P16)/$L$10) -> 0.095473398 | R17: NOI | U17: =U9-U16 -> 85038 | V17: =V9-V16 -> 120102 | Y17: 9 | Z17: =Z$6*((1+Z$5)^(Y17-1)) -> 17645.241
B18: 10 | H18: Capitalization Rate | I18: =I17/L8 -> 0.083284 | K18: Annualized ROI | L18: =L17/(L10+L11) -> 0.0018564906 | R18: Mortgage | U18: =L15*12 -> 124563.98 | V18: =U18 -> 124563.98 | Y18: 10 | Z18: =Z$6*((1+Z$5)^(Y18-1)) -> 18262.825
B19: 11 | Y19: 11 | Z19: =Z$6*((1+Z$5)^(Y19-1)) -> 18902.023
B20: 12 | H20: Stabilized pro forma analysis | N20: Five Year Tax Deduction Summary | R20: Debt Coverage Ratio | U20: =U17/U18 -> 0.68268529 | V20: =V17/V18 -> 0.96417918 | Y20: 12 | Z20: =Z$6*((1+Z$5)^(Y20-1)) -> 19563.594
B21: 13 | H21: MARKET RATE ANALYSIS | N21: Improved Value: Assessed Value Ratio (%) | P21: 0.8 | R21: Net Profit | U21: =U17-U18 -> -39525.984 | V21: =V17-V18 -> -4461.9843 | Y21: 13 | Z21: =Z$6*((1+Z$5)^(Y21-1)) -> 20248.32
B22: 14 | H22: Item | I22: $/Mo. | K22: Mortgage Calculator | N22: Marginal Tax Rate | P22: 0.33 | Y22: 14 | Z22: =Z$6*((1+Z$5)^(Y22-1)) -> 20957.011
B23: 15 | H23: Gross Rents | I23: =F29 -> 13400 | K23: Sale Price | L23: =C5 -> 1500000 | R23: Average Annualized % Appreciation | Y23: 15 | Z23: =Z$6*((1+Z$5)^(Y23-1)) -> 21690.507
H24: Property Management | I24: =C$40*I23 -> 0 | K24: Loan to Value Ratio | L24: =1-E$33 -> 0.9 | O24: Year | P24: Figure | R24: Assumed Rate: | S24: 0.035 | Y24: 16 | Z24: =Z$6*((1+Z$5)^(Y24-1)) -> 22449.674
H25: Property Taxes | I25: =C$33/12 -> 787.5 | K25: Down Payment | L25: =E33*L23 -> 150000 | N25: Depreciation (Straight Line) | O25: 1 | P25: =(P21*$L$8)/27.5 -> 43636.364 | Y25: 17 | Z25: =Z$6*((1+Z$5)^(Y25-1)) -> 23235.413
H26: Insurance | I26: =C$34 -> 32 | K26: Closing Costs | L26: =E$36 -> 45000 | N26: Total Interest Paid | O26: 1 | P26: =-CUMIPMT($L$13/12,$L$14*12,$L$12,(1+(12*(O26-1))),(12*O26),0) -> 114358.49 | R26: End of Year: | S26: Est. Value | T26: Annual Gain | U26: % Gain | Y26: 18 | Z26: =Z$6*((1+Z$5)^(Y26-1)) -> 24048.652
H27: Owner-Paid Utilities | I27: =SUM(C$35:C$39) -> 1500 | K27: Principal | L27: =L23*L24 -> 1350000 | N27: Total Deductions | O27: 1 | P27: =SUM($P$25+$P26) -> 157994.85 | R27: 1 | S27: =L8+(L8*$S$24) -> 1552500 | T27: =S27-L8 -> 52500 | U27: =T27/$L$10 -> 0.35 | Y27: 19 | Z27: =Z$6*((1+Z$5)^(Y27-1)) -> 24890.355
H28: Vacancy Reserve | I28: =C$41*I23 -> 0 | K28: Interest Rate | L28: =E$34 -> 0.085 | N28: Depreciation (Straight Line) | O28: 2 | P28: =(P21*$L$8)/27.5 -> 43636.364 | R28: 2 | S28: =S27+(S27*$S$24) -> 1606837.5 | T28: =S28-S27 -> 54337.5 | U28: =T28/$L$10 -> 0.36225 | Y28: 20 | Z28: =Z$6*((1+Z$5)^(Y28-1)) -> 25761.518
B29: Totals | E29: =SUM(E9:E28) -> 13400 | F29: =SUM(F9:F28) -> 13400 | H29: Maintenance Reserve | I29: =C42*I23 -> 670 | K29: Term (Years) | L29: =E$35 -> 30 | N29: Total Interest Paid | O29: 2 | P29: =-CUMIPMT($L$13/12,$L$14*12,$L$12,(1+(12*(O29-1))),(12*O29),0) -> 113456.42 | R29: 3 | S29: =S28+(S28*$S$24) -> 1663076.8 | T29: =S29-S28 -> 56239.312 | U29: =T29/$L$10 -> 0.37492875
H30: Total Operating Expenses | I30: =SUM(I24:I29) -> 2989.5 | K30: Monthly Mortgage | L30: =-pmt(L28/12,L29*12, L27) -> 10380.332 | N30: Total Deductions | O30: 2 | P30: =SUM($P$25+$P29) -> 157092.78 | R30: 4 | S30: =S29+(S29*$S$24) -> 1721284.5 | T30: =S30-S29 -> 58207.688 | U30: =T30/$L$10 -> 0.38805126
B31: Expenses | D31: Mortgage | H31: Monthly NOI | I31: =I23-I30 -> 10410.5 | K31: Monthly Net | L31: =I31-L30 -> 30.167972 | N31: Depreciation (Straight Line) | O31: 3 | P31: =(P21*$L$8)/27.5 -> 43636.364 | R31: 5 | S31: =S30+(S30*$S$24) -> 1781529.5 | T31: =S31-S30 -> 60244.958 | U31: =T31/$L$10 -> 0.40163305
H32: Annualized NOI | I32: =I31*12 -> 124926 | K32: Annualized Net | L32: =L31*12 -> 362.01566 | N32: Total Interest Paid | O32: 3 | P32: =-CUMIPMT($L$13/12,$L$14*12,$L$12,(1+(12*(O32-1))),(12*O32),0) -> 112474.61
B33: Property Tax/Yr | C33: =0.0063*F5 -> 9450 | D33: Downpayment (%) | E33: 0.1 | H33: Capitalization Rate | I33: =I32/L23 -> 0.083284 | K33: Annualized ROI | L33: =L32/(L25+L26) -> 0.0018564906 | N33: Total Deductions | O33: 3 | P33: =SUM($P$25+$P32) -> 156110.97 | R33: Total Return (% of initial investment)
B34: Insurance/Mo | C34: 32 | D34: Interest Rate (%) | E34: 0.085 | N34: Depreciation (Straight Line) | O34: 4 | P34: =(P21*$L$8)/27.5 -> 43636.364 | R34: Year | S34: 1 | T34: 2 | U34: 3 | V34: 4 | W34: 5
B35: Gas & Electric/Mo | C35: 500 | D35: Loan Term (Years) | E35: 30 | N35: Total Interest Paid | O35: 4 | P35: =-CUMIPMT($L$13/12,$L$14*12,$L$12,(1+(12*(O35-1))),(12*O35),0) -> 111406.02 | R35: Source of Gain
B36: Water/Mo | C36: 200 | D36: Closing Costs | E36: =0.03*C5 -> 45000 | F36: Estimated 3% for closing | N36: Total Deductions | O36: 4 | P36: =SUM($P$25+$P35) -> 155042.38 | R36: Cash flow | S36: =$L$33 -> 0.0018564906 | T36: =$L$33 -> 0.0018564906 | U36: =$L$33 -> 0.0018564906 | V36: =$L$33 -> 0.0018564906 | W36: =$L$33 -> 0.0018564906
B37: Sewer/Mo | C37: 200 | N37: Depreciation (Straight Line) | O37: 5 | P37: =(P21*$L$8)/27.5 -> 43636.364 | R37: Debt Paydown | S37: =P9 -> 0.068036625 | T37: =P11 -> 0.074050444 | U37: =P13 -> 0.08059583 | V37: =P15 -> 0.087719768 | W37: =P17 -> 0.095473398
B38: Garbage/Mo | C38: 300 | N38: Total Interest Paid | O38: 5 | P38: =-CUMIPMT($L$13/12,$L$14*12,$L$12,(1+(12*(O38-1))),(12*O38),0) -> 110242.97 | R38: Tax Savings | S38: =(P27*P22)/L10 -> 0.34758868 | T38: =(P30*P22)/L10 -> 0.34560412 | U38: =(P33*P22)/L10 -> 0.34344414 | V38: =(P36*P22)/L10 -> 0.34109324 | W38: =(P39*P22)/L10 -> 0.33853454
B39: Lawn and Snow | C39: 300 | N39: Total Deductions | O39: 5 | P39: =SUM($P$25+$P38) -> 153879.34 | R39: Appreciation | S39: =U27 -> 0.35 | T39: =U28 -> 0.36225 | U39: =U29 -> 0.37492875 | V39: =U30 -> 0.38805126 | W39: =U31 -> 0.40163305
B40: Management (%) | C40: 0 | N40: Avg Yearly Tax Savings | P40: =(AVERAGE(P27,P30,P33,P36,P39))*P22 -> 51487.942 | R40: Total ROI | S40: =SUM(S36:S39) -> 0.76748179 | T40: =SUM(T36:T39) -> 0.78376105 | U40: =SUM(U36:U39) -> 0.80082521 | V40: =SUM(V36:V39) -> 0.81872076 | W40: =SUM(W36:W39) -> 0.83749748
B41: Vacancy (%) | C41: 0 | N41: % Annual ROI on Tax Savings | P41: =P40/L10 -> 0.34325295 | R41: Total $ Return | S41: =S40*$L$10 -> 115122.27 | T41: =T40*$L$10 -> 117564.16 | U41: =U40*$L$10 -> 120123.78 | V41: =V40*$L$10 -> 122808.11 | W41: =W40*$L$10 -> 125624.62
B42: Maintenance (%) | C42: 0.05

Sheet Deal Analyzer Fields
A1: Section | B1: Field Name | C1: Current Value | D1: Manual/Formula | E1: Where to find the information? | G1: Manual | H1: INTERNAL ONLY
A2: PROPERTY VALUES/PRICING | B2: Estimated Hold Time months : | C2: 2 | D2: Manual | E2: Contractor + Realtor | G2: Formula | H2: - - - - - - - - - - - - - - - - - - - - - - -
A3: PROPERTY VALUES/PRICING | B3: Current "As-Is" Value: | C3: 45000 | D3: Manual | E3: Tax Assessment | G3: ------------ | H3: PROPERTY INFORMATION
A4: PROPERTY VALUES/PRICING | B4: Purchase Price: | C4: 71000 | D4: Manual | E4: Purchase Agreement/ or estimate | H4: PROPERTY VALUES/PRICING
A5: PROPERTY VALUES/PRICING | B5: Estimated Repair Costs: | C5: 32000 | D5: Manual | E5: Quotes from Handymen/ General Contractor | H5: DEAL SUMMARY & POTENTIAL PROFIT
A6: PROPERTY VALUES/PRICING | B6: After Repair Value: | C6: 140000 | D6: Manual | E6: Comparative Analysis or Apprasial | H6: FINANCING PROJECTION
A7: PROPERTY VALUES/PRICING | B7: PURCHSE AND REPAIR COSTS: | C7: -103000 | D7: Formula | E7: Formula | H7: HOLDING COSTS
A8: DEAL SUMMARY & POTENTIAL PROFIT | B8: Total Financing Costs: | C8: 8400 | D8: Formula | E8: Formula | H8: SELLING TRANSACTION COSTS
A9: DEAL SUMMARY & POTENTIAL PROFIT | B9: Total Holding Costs | C9: 3862 | D9: Formula | E9: Formula | H9: NOTES
A10: DEAL SUMMARY & POTENTIAL PROFIT | B10: Total Buying Transaction Costs: | C10: 2800 | D10: Formula | E10: Formula | H10: BUYING TRANSACTION COSTS
A11: DEAL SUMMARY & POTENTIAL PROFIT | B11: Total Selling Transaction Costs: | C11: 6285 | D11: Formula | E11: Formula
A12: DEAL SUMMARY & POTENTIAL PROFIT | B12: ESTIMATED NET PROFIT: | C12: 15653 | D12: Formula
A13: FINANCING PROJECTION | B13: First Mortgage / Lien Amount: Amount | C13: 120000 | D13: Manual | E13: Hard Money or Private Lender/ Mortgage Broker/ Friend
A14: FINANCING PROJECTION | B14: First Mortgage Points: Rate | C14: 0.04 | D14: Manual | E14: Hard Money or Private Lender/ Mortgage Broker/ Friend
A15: FINANCING PROJECTION | B15: First Mortgage Interest: Rate | C15: 0 | D15: Manual | E15: Hard Money or Private Lender/ Mortgage Broker/ Friend
A16: FINANCING PROJECTION | B16: First Mortgage Monthly Interest Only Payment: Rate | C16: 0.015 | D16: Manual | E16: Hard Money or Private Lender/ Mortgage Broker/ Friend
A17: FINANCING PROJECTION | B17: Second Mortgage / Lien Amount: Rate | C17: 0 | D17: Manual | E17: Hard Money or Private Lender/ Mortgage Broker/ Friend
A18: FINANCING PROJECTION | B18: Second Mortgage Points: Rate | C18: 0 | D18: Manual | E18: Hard Money or Private Lender/ Mortgage Broker/ Friend
A19: FINANCING PROJECTION | B19: Second Mortgage Interest: Rate | C19: 0 | D19: Manual | E19: Hard Money or Private Lender/ Mortgage Broker/ Friend
A20: FINANCING PROJECTION | B20: Second Mortgage Monthly Interest Only Payment: Rate | C20: 0 | D20: Manual | E20: Hard Money or Private Lender/ Mortgage Broker/ Friend
A21: FINANCING PROJECTION | B21: Misc. Mortgage / Lien Amount: Rate | C21: 0 | D21: Manual | E21: Hard Money or Private Lender/ Mortgage Broker/ Friend
A22: FINANCING PROJECTION | B22: Misc. Mortgage Points: Rate | C22: 0 | D22: Manual | E22: Hard Money or Private Lender/ Mortgage Broker/ Friend
A23: FINANCING PROJECTION | B23: Misc. Mortgage Interest: Rate | C23: 0 | D23: Manual | E23: Hard Money or Private Lender/ Mortgage Broker/ Friend
A24: FINANCING PROJECTION | B24: Misc. Mortgage Monthly Interest Only Payment: Rate | C24: 0 | D24: Manual | E24: Hard Money or Private Lender/ Mortgage Broker/ Friend
... A55: HOLDING COSTS | B55: Miscellaneous Annualized | C55: 0 | D55: Formula | E55: Formula
A56: HOLDING COSTS | B56: Total Maintenance Costs | C56: 3862 | D56: Formula
A57: HOLDING COSTS | B57: Miscellaneous Holding Costs Annualized | C57: 0 | D57: Manual | E57: Miscellaneous
A58: HOLDING COSTS | B58: Miscellaneous Holding Costs Annualized | C58: 0 | D58: Manual | E58: Miscellaneous
A59: HOLDING COSTS | B59: Miscellaneous Holding Costs Annualized | C59: 0 | D59: Manual | E59: Miscellaneous
A60: HOLDING COSTS | B60: Miscellaneous Holding Costs Annualized | C60: 0 | D60: Manual | E60: Miscellaneous
A61: HOLDING COSTS | B61: TOTAL HOLDING COSTS: | C61: 0 | D61: Formula | E61: Formula
A62: BUYING TRANSACTION COSTS | B62: Escrow / Attorney Fees Rate | C62: 0.01 | D62: Manual | E62: The Attorney
A63: BUYING TRANSACTION COSTS | B63: Title Insurance / Search Costs Rate | C63: 0.01 | D63: Manual | E63: Title Company
A64: BUYING TRANSACTION COSTS | B64: Miscellaneous Buying Costs Rate | C64: 0 | D64: Manual | E64: Miscellaneous
A65: BUYING TRANSACTION COSTS | B65: Escrow / Attorney Fees Annualized | C65: 1400 | D65: Formula | E65: Formula
A66: BUYING TRANSACTION COSTS | B66: Title Insurance / Search Costs Annualized | C66: 1400 | D66: Formula | E66: Formula
A67: BUYING TRANSACTION COSTS | B67: Miscellaneous Buying Costs Annualized | C67: 0 | D67: Formula | E67: Formula
A68: SELLING TRANSACTION COSTS | B68: Escrow / Attorney Fees Rate | C68: 0.02 | D68: Manual | E68: The Attorney
... A79: SELLING TRANSACTION COSTS | B79: Miscellaneous Selling Costs Annualized | C79: 0 | D79: Formula | E79: Formula
A80: NOTES | B80: Notes | C80: NADA | D80: ------------
A81: INTERNAL ONLY | B81: 70% of ARV | C81: 98000 | D81: Formula | E81: Formula
A82: INTERNAL ONLY | B82: Assignment Fee | C82: 5000 | D82: Manual | E82: How Much You wanna Make
A83: INTERNAL ONLY | B83: All In Max Limit | C83: 103000 | D83: Formula | E83: Formula
A84: INTERNAL ONLY | B84: Repair Costs | C84: -32000 | D84: Formula | E84: Formula
A85: INTERNAL ONLY | B85: Offer | C85: 71000 | D85: Formula | E85: Formula
A86: INTERNAL ONLY | B86: % of ARV | C86: 0.50714286 | D86: Formula | E86: Formula
A88: - - - - - - - - - - - - - - - - - - - - - - - | D88: ------------
A89: - - - - - - - - - - - - - - - - - - - - - - - | D89: ------------
A90: - - - - - - - - - - - - - - - - - - - - - - - | D90: ------------
A91: - - - - - - - - - - - - - - - - - - - - - - - | D91: ------------
A92: - - - - - - - - - - - - - - - - - - - - - - - | D92: ------------
A93: - - - - - - - - - - - - - - - - - - - - - - - | D93: ------------
A94: - - - - - - - - - - - - - - - - - - - - - - - | D94: ------------
A95: - - - - - - - - - - - - - - - - - - - - - - - | D95: ------------
A96: - - - - - - - - - - - - - - - - - - - - - - - | D96: ------------
A97: - - - - - - - - - - - - - - - - - - - - - - - | D97: ------------
A98: - - - - - - - - - - - - - - - - - - - - - - - | D98: ------------
A99: - - - - - - - - - - - - - - - - - - - - - - - | D99: ------------
... A111: - - - - - - - - - - - - - - - - - - - - - - - | D111: ------------

Sheet To Airtable
A1: Name | B1: Property | C1: Estimated Hold Time months : | D1: Current "As-Is" Value: | E1: Purchase Price: | F1: Estimated Repair Costs: | G1: After Repair Value: | H1: PURCHSE AND REPAIR COSTS: | I1: Total Financing Costs: | J1: Total Holding Costs | K1: Total Buying Transaction Costs: | L1: Total Selling Transaction Costs: | M1: ESTIMATED NET PROFIT: | N1: First Mortgage / Lien Amount: Amount | O1: First Mortgage Points: Rate | P1: First Mortgage Interest: Rate | Q1: First Mortgage Monthly Interest Only Payment: Rate | R1: Second Mortgage / Lien Amount: Rate | S1: Second Mortgage Points: Rate | T1: Second Mortgage Interest: Rate | U1: Second Mortgage Monthly Interest Only Payment: Rate | V1: Misc. Mortgage / Lien Amount: Rate | W1: Misc. Mortgage Points: Rate | X1: Misc. Mortgage Interest: Rate | Y1: Misc. Mortgage Monthly Interest Only Payment: Rate | Z1: Miscellaneous Financing Costs: Rate | AA1: First Mortgage / Lien Amount: Amount Paid | AB1: First Mortgage Points: Amount Paid | AC1: First Mortgage Interest: Amount Paid | AD1: First Mortgage Monthly Interest Only Payment: Amount Paid | AE1: Second Mortgage / Lien Amount: Amount Paid | AF1: Second Mortgage Points: Amount Paid | AG1: Second Mortgage Interest: Amount Paid | AH1: Second Mortgage Monthly Interest Only Payment: Amount Paid | AI1: Misc. Mortgage / Lien Amount: Amount Paid | AJ1: Misc. Mortgage Points: Amount Paid | AK1: Misc. Mortgage Interest: Amount Paid | AL1: Misc. Mortgage Monthly Interest Only Payment: Amount Paid | AM1: Miscellaneous Financing Costs: Amount Paid | AN1: TOTAL FINANCING COSTS: | AO1: Property Taxes Rate | AP1: HOA & Condo Fees Monthly Amount | AQ1: Insurance Costs Monthly Amount | AR1: Utilities Monthly Amount | AS1: Gas Monthly Amount | AT1: Water Monthly Amount | AU1: Electricity Monthly Amount | AV1: Miscellaneous Monthly Amount | AW1: Property Taxes Annualized | AX1: HOA & Condo Fees Annualized | AY1: Insurance Costs Annualized | AZ1: Utilities Annualized | BA1: Gas Annualized | BB1: Water Annualized | BC1: Electricity Annualized | BD1: Miscellaneous Annualized | BE1: Total Maintenance Costs | BF1: Miscellaneous Holding Costs Annualized | BG1: Miscellaneous Holding Costs Annualized | BH1: Miscellaneous Holding Costs Annualized | BI1: Miscellaneous Holding Costs Annualized | BJ1: TOTAL HOLDING COSTS: | BK1: Escrow / Attorney Fees Rate | BL1: Title Insurance / Search Costs Rate | BM1: Miscellaneous Buying Costs Rate | BN1: Escrow / Attorney Fees Annualized | BO1: Title Insurance / Search Costs Annualized | BP1: Miscellaneous Buying Costs Annualized | BQ1: Escrow / Attorney Fees Rate | BR1: Selling Recording Fees Rate | BS1: Realtor Fees Rate | BT1: Transfer & Conveyance Fees Rate | BU1: Escrow / Attorney Fees Annualized | BV1: Selling Recording Fees Annualized | BW1: Realtor Fees Annualized | BX1: Transfer & Conveyance Fees Annualized | BY1: Home Warranty Annualized | BZ1: Staging Costs Annualized | CA1: Marketing Costs Annualized | CB1: Miscellaneous Selling Costs Annualized | CC1: Notes | CD1: 70% of ARV | CE1: Assignment Fee | CF1: All In Max Limit | CG1: Repair Costs | CH1: Offer | CI1: % of ARV
A2: Address + Potential Profit = "$$,$$$" | B2: Current Value | C2: 2 | D2: 45000 | E2: 71000 | F2: 32000 | G2: 140000 | H2: -103000 | I2: 8400 | J2: 3862 | K2: 2800 | L2: 6285 | M2: 15653 | N2: 120000 | O2: 0.04 | P2: 0 | Q2: 0.015 | R2: 0 | S2: 0 | T2: 0 | U2: 0 | V2: 0 | W2: 0 | X2: 0 | Y2: 0 | Z2: 0 | AA2: 0 | AB2: 4800 | AC2: 0 | AD2: 3600 | AE2: 0 | AF2: 0 | AG2: 0 | AH2: 0 | AI2: 0 | AJ2: 0 | AK2: 0 | AL2: 0 | AM2: 0 | AN2: 8400 | AO2: 0.022 | AP2: 0 | AQ2: 500 | AR2: 0 | AS2: 56 | AT2: 24 | AU2: 76 | AV2: 0 | AW2: 990 | AX2: 0 | AY2: 1000 | AZ2: 0 | BA2: 672 | BB2: 288 | BC2: 912 | BD2: 0 | BE2: 3862 | BF2: 0 | BG2: 0 | BH2: 0 | BI2: 0 | BJ2: 0 | BK2: 0.01 | BL2: 0.01 | BM2: 0 | BN2: 1400 | BO2: 1400 | BP2: 0 | BQ2: 0.02 | BR2: 0.005 | BS2: 0 | BT2: 0.03 | BU2: 2800 | BV2: 355 | BW2: 0 | BX2: 2130 | BY2: 1000 | BZ2: 0 | CA2: 0 | CB2: 0 | CC2: NADA | CD2: 98000 | CE2: 5000 | CF2: 103000 | CG2: -32000 | CH2: 71000 | CI2: 0.50714286

Sheet Example
A1: Real Property Analysis
A2: Date: | B2: 43601
A3: Evaluator Name:
A5: PROPERTY INFORMATION
A6: Property Address: | B6: Margaret Avenue Essex, MD 21221
A7: Total Square Footage: | B7: 936
A8: # of Units: | B8: 1
A9: Occupied? Y/N | B9: N
A10: Property Description: Detached home in Essex with 3 bedrooms on the 1st floor & loft bedroom on the 2nd floor. Large yard with off-street parking & separate garage
A14: PROPERTY VALUES/PRICING
A15: After Repair Value | B15: 200000
A16: Current "As Is" Value | B16: 0
A17: Estimated Repair Costs | B17: 40000
A18: Purchase Price | B18: 121870
A19: Estimated Hold Time months | B19: 6
A20: PURCHASE and REPAIR COSTS | B20: 161870
A22: PROJECT FINANCING COSTS
A23: First Mortgage / Lien Amount | B23: 1 | C23: 161870
A24: First Mortgage Points | B24: 4 | C24: 6474.8
A25: First Mortgage Interest | B25: 0.14 | C25: 11330.9
A26: First Mortgage Monthly Interest Only Payment | C26: 1888.4833
A28: Second Mortgage / Lien Amount | B28: 0 | C28: 0
A29: Second Mortgage Points | B29: 0 | C29: 0
A30: Second Mortgage Interest | B30: 0 | C30: 0
A31: Second Mortgage Monthly Interest Only Payment | C31: 0
A33: Misc. Mortgage / Lien Amount | B33: 0 | C33: 0
A34: Misc. Mortgage Points | B34: 0 | C34: 0
A35: Misc. Mortgage Interest | B35: 0 | C35: 0
A36: Misc. Mortgage Monthly Interest Only Payment | C36: 0
A37: Miscellaneous Financing Costs | C37: 0
A39: TOTAL FINANCING COSTS | C39: 17805.7
A41: HOLDING COSTS
B42: Annualized | C42: Monthly
A43: Property Taxes | B43: 1200 | C43: 100
A44: HOA & Condo Fees | B44: 0 | C44: 0
A45: Insurance Costs | B45: 1050 | C45: 87.5
A46: Utilities
A47: Gas | C47: 75
A48: Water | C48: 75
A49: Electricity | C49: 50
A50: Miscellaneous | C50: 0
A51: Total Utility Costs | C51: 200
A52: Miscellaneous Holding Costs | C52: 0
A53: TOTAL MONTHLY HOLDING COSTS | C53: 387.5
A55: BUYING TRANSACTION COSTS
B56: % of Purchase | C56: Total
A57: Escrow / Attorney Fees | C57: 900
A58: Title Insurance / Search Costs | B58: 0.0025 | C58: 804.675
A59: Miscellaneous Buying Costs | C59: 0
A60: TOTAL BUYING TRANSACTION COSTS | C60: 1704.675
A62: SELLING TRANSACTION COSTS
B63: % of Purchase | C63: Total
A64: Escrow / Attorney Fees | C64: 1300
A65: Selling Recording Fees | B65: 0.005 | C65: 1000
A66: Realtor Fees | B66: 0 | C66: 0
A67: Transfer & Conveyance Fees | B67: 0.015 | C67: 3000
A68: Home Warranty | C68: 0
A69: Staging Costs | C69: 0
A70: Marketing Costs | C70: 0
A71: Miscellaneous Selling Costs | C71: 0
A72: TOTAL SELLING TRANSACTION COSTS | C72: 5300
A75: ESTIMATED NET PROFIT and ROI SNAPSHOT
A76: DEAL SUMMARY & POTENTIAL PROFIT
A77: After Repair Value | B77: 200000
A78: Purchase Price | B78: 121870
A79: Estimated Repair Costs | B79: 40000
A80: Total Financing Costs | B80: 17805.7
A81: Total Holding Costs | B81: 2325
A82: Total Buying Transaction Costs | B82: 1704.675
A83: Total Selling Transaction Costs | B83: 5300
A85: ESTIMATED NET PROFIT | B85: 10994.625
A87: TOTAL COSTS RETURN ON INVESTMENT ROI
A88: POTENTIAL RETURN & PROFIT ANALYSIS
A89: Assumes Sale is on or before | B89: 43781
A90: Purchase + Repair Estimate Cost Per Sq. Ft | B90: 172.93803
A91: Down Payment Required at Closing
A92: My Committed Capital | B92: 10504.475
A93: Purchase + Rehab Return on Investment ROI | B93: 0.067922561
A95: ESTIMATED RETURN ON INVESTMENT | B95: 0.058170965

Sheet Example 2
A1: Real Property Analysis
A2: Date: | B2: =today() -> 46279
A3: Evaluator Name:
A5: PROPERTY INFORMATION
A6: Property Address: | B6: 7800 Block of Bagley Avenue, Parkville, MD 21234 | E6: https://docs.google.com/document/d/1nlNMYw44OTGcmdOozJGbRqV0EkmI2NJo40TqVi59hRg/edit
A7: Total Square Footage: | B7: 1000 | E7: * this property is just under 1k sq ft.
A8: # of Units: | B8: 1
A9: Occupied? Y/N | B9: N
A10: This is a detached property with off-street parking, full basement, sunroom off the rear and 2nd floor loft bedroom that can has space to create a potential master suite with bathroom. Sold AS-IS.
A14: PROPERTY VALUES/PRICING
A15: After Repair Value | B15: 180000
A16: Current "As Is" Value | B16: 0
A17: Estimated Repair Costs | B17: 15950 | E17: @40,600 which is based on 1200 sq ft.
A18: Purchase Price | B18: 130450
A19: Estimated Hold Time months | B19: 6
A20: PURCHASE and REPAIR COSTS | B20: =B17+B18 -> 146400
A22: Project Financing Projection
A23: First Mortgage / Lien Amount | B23: 1 | C23: =B20 -> 146400
A24: First Mortgage Points | B24: 4 | C24: =B24/100*C23 -> 5856
A25: First Mortgage Interest | B25: 0.14 | C25: =C23*B25/12*B19 -> 10248
A26: First Mortgage Monthly Interest Only Payment | C26: =C25/B19 -> 1708
A28: Second Mortgage / Lien Amount | B28: 0 | C28: 0
A29: Second Mortgage Points | B29: 0 | C29: =B29/100*C28 -> 0
A30: Second Mortgage Interest | B30: 0 | C30: =C28*B30/12*B19 -> 0
A31: Second Mortgage Monthly Interest Only Payment | C31: =C30/B19 -> 0
A33: Misc. Mortgage / Lien Amount | B33: 0 | C33: 0
A34: Misc. Mortgage Points | B34: 0 | C34: =B34/100*C33 -> 0
A35: Misc. Mortgage Interest | B35: 0 | C35: =C33*B35/12*B19 -> 0
A36: Misc. Mortgage Monthly Interest Only Payment | C36: =C35/B19 -> 0
A37: Miscellaneous Financing Costs | C37: 0
A39: TOTAL FINANCING COSTS | C39: =C24+C25+C29+C30+C34+C35+C37 -> 16104
A41: HOLDING COSTS
B42: Annualized | C42: Monthly
A43: Property Taxes | B43: 1200 | C43: =B43/12 -> 100
A44: HOA & Condo Fees | B44: =C44*12 -> 0 | C44: 0
A45: Insurance Costs | B45: 1050 | C45: =B45/12 -> 87.5
A46: Utilities
A47: Gas | C47: 75
A48: Water | C48: 75
A49: Electricity | C49: 50
A50: Miscellaneous | C50: 0
A51: Total Utility Costs | C51: =C50+C49+C48+C47 -> 200
A52: Miscellaneous Holding Costs | C52: 0
A53: TOTAL MONTHLY HOLDING COSTS | C53: =C43+C44+C45+C51+C52 -> 387.5
A55: BUYING TRANSACTION COSTS
B56: % of Purchase | C56: Total
A57: Escrow / Attorney Fees | C57: 900 | E57: Blue is unknown. estimated.
A58: Title Insurance / Search Costs | B58: 0.0025 | C58: =(500)+(B58*B18) -> 826.125
A59: Miscellaneous Buying Costs | C59: 0
A60: TOTAL BUYING TRANSACTION COSTS | C60: =SUM(C57:C59) -> 1726.125
A62: SELLING TRANSACTION COSTS
B63: % of Purchase | C63: Total
A64: Escrow / Attorney Fees | C64: 1300
A65: Selling Recording Fees | B65: 0.005 | C65: =B65*B15 -> 900
A66: Realtor Fees | B66: 0 | C66: =B66*B15 -> 0
A67: Transfer & Conveyance Fees | B67: 0.015 | C67: =B67*B15 -> 2700
A68: Home Warranty | C68: 0
A69: Staging Costs | C69: 0
A70: Marketing Costs | C70: 0
A71: Miscellaneous Selling Costs | C71: 0
A72: TOTAL SELLING TRANSACTION COSTS | C72: =SUM(C64:C71) -> 4900
A75: ESTIMATED NET PROFIT and ROI SNAPSHOT
A76: DEAL SUMMARY & POTENTIAL PROFIT
A77: After Repair Value | B77: =B15 -> 180000
A78: Purchase Price | B78: =B18 -> 130450
A79: Estimated Repair Costs | B79: =B17 -> 15950
A80: Total Financing Costs | B80: =C24+C25+C29+C30+C34+C35+C37 -> 16104
A81: Total Holding Costs | B81: =C53*B19 -> 2325
A82: Total Buying Transaction Costs | B82: =SUM(C57:C59) -> 1726.125
A83: Total Selling Transaction Costs | B83: =SUM(C64:C71) -> 4900
A85: ESTIMATED NET PROFIT | B85: =B77-B78-B79-B80-B81-B82-B83 -> 8544.875
A87: TOTAL COSTS RETURN ON INVESTMENT ROI
A88: POTENTIAL RETURN & PROFIT ANALYSIS
A89: Assumes Sale is on or before | B89: =B2+(B19*30) -> 46459
A90: Purchase + Repair Estimate Cost Per Sq. Ft | B90: =(B78+B79)/B7 -> 146.4
A91: Down Payment Required at Closing
A92: My Committed Capital | B92: =C24 -> 5856 | E92: Depends on the Hard Money Lender Used*
A93: Purchase + Rehab Return on Investment ROI | B93: =B85/(B78+B79) -> 0.058366633
A95: ESTIMATED RETURN ON INVESTMENT | B95: =B85/(B78+B79+B80+B81+B82+B83) -> 0.049837385

Sheet Rehab Estimator Fields
B1: Section | C1: Field Name | D1: Current Value | E1: Manual/Formula | F1: Where to find the information? | I1: Sections
B2: Need a Roof? | C2: Does This House Need a Roof? | D2: Yes/No | I2: Need a Roof?
C3: Is this a single family or a multi unit? | D3: Single/Multi
C4: Shingles? | D4: 1 Layer Low/1 Layer High | I4: Need Windows?
I5: Garage Repair?
C6: Does this House Need Exterion Paint/Siding? | I6: Yard Cleaned/Landscapes
I7: Heating or Furnaces Need Replacing?
I8: Plumbimg need Repair?
I9: Electrical Need Repair
I10: Foundation Need Repair?
I11: Basement Need Repair?
I12: Need Interior Paint
I13: House Need Carpet?
I14: House Need Tile/Vinyl
I15: Floor need to be sanded?
I16: Unit 1 Kitchen Need Repair
I17: Unit 2 Kitcken Need Repair?
I18: Unit 3 Kitchen Need Repair?
... I26: Miscellaneous

Sheet Rehab Estimator
B1: Address: Bagley Avenue | E1: Yes | F1: No | G1: TOTAL ESTIMATED REPAIR COST | I1: =sum(I2:I69) -> 20050 | J1: Home Renovation Cost Estimates
B2: Inspections Checklist | E2: Yes/No | F2: # of Units | G2: Repair Cost Calculations | I2: Repair Cost | J2: https://homeguide.com/costs/house-remodeling-cost
A3: 1 | B3: Need a Roof? | E3: Yes | F3: 1 | G3: Single? | H3: 6000 | I3: =if(E3="Yes",H3*F3,0) -> 6000
F4: 0 | G4: Full Roof Multi Unit | H4: 9000 | I4: =if(E4="Yes",H4*F4,0) -> 0
F5: 0 | G5: 1 Layer of Shingles Added Low | H5: 2500 | I5: =if(E5="Yes",H5*F5,0) -> 0
F6: 0 | G6: 1 Layer of Shingles Added High | H6: 3000 | I6: =if(E6="Yes",H6*F6,0) -> 0
A7: 2 | B7: Exterion Paint/Siding? | E7: Yes | F7: 1 | G7: Paint Single Fam Home | H7: 3000 | I7: =if(E7="Yes",H7*F7,0) -> 3000
F8: 0 | G8: Paint Multi Fam Low 1500sq ft | H8: 6000 | I8: =if(E8="Yes",H8*F8,0) -> 0
F9: 0 | G9: Paint Multi Fam Low 3000sq ft | H9: 7000 | I9: =if(E9="Yes",H9*F9,0) -> 0
F10: 0 | G10: Sinding Single Fam Low 1500sq ft | H10: 7000 | I10: =if(E10="Yes",H10*F10,0) -> 0
F11: 0 | G11: Siding Multi Fam Low 3000sq ft | H11: 11000 | I11: =if(E11="Yes",H11*F11,0) -> 0
A12: 3 | B12: Need Windows? | E12: Yes | F12: 20 | G12: Cost/Window | H12: 250 | I12: =if(E12="Yes",H12*F12,0) -> 5000
A13: 4 | B13: Garage Repair? | E13: Yes | F13: 1 | G13: Garage Door | H13: 550 | I13: =if(E13="Yes",H13*F13,0) -> 550
F14: 0 | G14: Reframe Stucture | H14: 1500 | I14: =if(E14="Yes",H14*F14,0) -> 0
F15: 0 | G15: 1 Car Garage Paint | H15: 500 | I15: =if(E15="Yes",H15*F15,0) -> 0
F16: 0 | G16: 2 Car Garage Paint | H16: 1000 | I16: =if(E16="Yes",H16*F16,0) -> 0
F17: 0 | G17: Roof | H17: 2000 | I17: =if(E17="Yes",H17*F17,0) -> 0
A18: 5 | B18: Yard Cleaned/Landscapes | E18: Yes | F18: 1 | G18: Clean Yard Easy | H18: 5000 | I18: =if(E18="Yes",H18*F18,0) -> 5000
F19: 0 | G19: Clean Yard Hard | H19: 750 | I19: =if(E19="Yes",H19*F19,0) -> 0
E20: Yes | F20: 1 | G20: Landscape Easy | H20: 500 | I20: =if(E20="Yes",H20*F20,0) -> 500
E21: No | F21: 0 | G21: Landscape Hard | H21: 1000 | I21: =if(E21="Yes",H21*F21,0) -> 0
A22: 6 | B22: Heating or Furnaces Need Replacing? | E22: No | F22: 1 | G22: Replace Furnace | H22: 1500 | I22: =if(E22="Yes",H22*F22,0) -> 0
E23: No | F23: 1 | G23: Replace Hot Water Heater | H23: 600 | I23: =if(E23="Yes",H23*F23,0) -> 0
G24: Install Zone Baseboard Heater Gut Job | H24: 4500 | I24: =if(E24="Yes",H24*F24,0) -> 0
A25: 7 | B25: Plumbimg need Repair? | E25: No | F25: 1 | G25: New Plumbimg/Floor | H25: 2500 | I25: =if(E25="Yes",H25*F25,0) -> 0
A26: 8 | B26: Electrical Need Repair | G26: New Panel | H26: 1500 | I26: =if(E26="Yes",H26*F26,0) -> 0
F27: 0 | G27: # of Floor Fixtures That needs new Fixtures | H27: 200 | I27: =if(E27="Yes",H27*F27,0) -> 0
F28: 0 | G28: #of floors Rewire House w/ New Service | H28: 4000 | I28: =if(E28="Yes",H28*F28,0) -> 0
A29: 9 | B29: Foundation Need Repair? | F29: 0 | G29: Reframe Support Beam | H29: 300 | I29: =if(E29="Yes",H29*F29,0) -> 0
A30: 10 | B30: Basement Need Repair? | F30: 0 | G30: Seal Basement | H30: 250 | I30: =if(E30="Yes",H30*F30,0) -> 0
F31: 0 | G31: # of 5yard Increments Pour Concrete Floor | H31: 800 | I31: =if(E31="Yes",H31*F31,0) -> 0
F32: 0 | G32: Replace Stairwell | H32: 1000 | I32: =if(E32="Yes",H32*F32,0) -> 0
F33: 0 | G33: Jack 1 Support Beam | H33: 200 | I33: =if(E33="Yes",H33*F33,0) -> 0
A34: 11 | B34: Need Interior Paint | E34: No | F34: 1400 | G34: # of square FT | H34: 2 | I34: =if(E34="Yes",H34*F34,0) -> 0
F35: 0 | G35: Single Family 1500 sf ft | H35: 2500 | I35: =if(E35="Yes",H35*F35,0) -> 0
F36: 0 | G36: Three Family Home 3000 sq ft | H36: 4500 | I36: =if(E36="Yes",H36*F36,0) -> 0
A37: 12 | B37: House Need Carpet? | E37: No | F37: 1 | G37: Single Family Carpet | H37: 1500 | I37: =if(E37="Yes",H37*F37,0) -> 0
A38: 13 | B38: House Need Tile/Vinyl | G38: Three Family Home | H38: 2000 | I38: =if(E38="Yes",H38*F38,0) -> 0
A39: 14 | B39: Floor need to be sanded? | F39: 0 | G39: 1 Unit Carpet 500 sq ft : $500 Carpet Rule:Sq ft. / 9 x $10=Cost | I39: =if(E39="Yes",H39*F39,0) -> 0
F40: 0 | G40: 1 Unit Carpet 500 sq ft : $500 Carpet Rule:Sq ft. / 9 x $10=Cost | I40: =if(E40="Yes",H40*F40,0) -> 0
F41: 0 | G41: 1 Kitchen Vinyl tiles 10x10 = $700 | I41: =if(E41="Yes",H41*F41,0) -> 0
F42: 0 | G42: Hardwood Install = $7.00 sq/ft Sand & Refinish= $2.75sq/ft | I42: =if(E42="Yes",H42*F42,0) -> 0
A43: 15 | B43: Unit 1 Kitchen Need Repair | E43: No | F43: 0 | G43: Single Fam Rental | H43: 2000 | I43: =if(E43="Yes",H43*F43,0) -> 0
A44: 16 | B44: Unit 2 Kitcken Need Repair? | F44: 0 | G44: Three Fam Rental | H44: 6000 | I44: =if(E44="Yes",H44*F44,0) -> 0
A45: 17 | B45: Unit 3 Kitchen Need Repair? | F45: 0 | G45: Single Fam Owner | H45: 3500 | I45: =if(E45="Yes",H45*F45,0) -> 0
F46: 0 | G46: Three Fam Owner | H46: 7500 | I46: =if(E46="Yes",H46*F46,0) -> 0
F47: 0 | G47: Single Family Nice | H47: 4000 | I47: =if(E47="Yes",H47*F47,0) -> 0
A48: 18 | B48: Kitchen Need Appliances? | F48: 0 | G48: Stove | H48: 350 | I48: =if(E48="Yes",H48*F48,0) -> 0
F49: 0 | G49: Refridgerator | H49: 500 | I49: =if(E49="Yes",H49*F49,0) -> 0
F50: 0 | G50: Overhead Microwave | H50: 200 | I50: =if(E50="Yes",H50*F50,0) -> 0
F51: 0 | G51: Dishwasher | H51: 250 | I51: =if(E51="Yes",H51*F51,0) -> 0
A52: 19 | B52: Unit 1 Bath need Repair? | E52: No | F52: 1 | G52: Redo Full Bath | H52: 1500 | I52: =if(E52="Yes",H52*F52,0) -> 0
A53: 20 | B53: Unit 2 Bath need Repair? | F53: 0 | G53: Redo Half Bath | H53: 1000 | I53: =if(E53="Yes",H53*F53,0) -> 0
A54: 21 | B54: Unit 3 Bath need Repair? | F54: 0 | G54: Fixtures only Full Bath | H54: 500 | I54: =if(E54="Yes",H54*F54,0) -> 0
F55: 0 | G55: Fixtures Only Half Bath | H55: 350 | I55: =if(E55="Yes",H55*F55,0) -> 0
A56: 22 | B56: Sheetrock damaged or Need Replacing? | F56: 0 | G56: # of Square FT Total Gut Job | H56: 3 | I56: =if(E56="Yes",H56*F56,0) -> 0
F57: 0 | G57: Single Fam Patch Low | H57: 500 | I57: =if(E57="Yes",H57*F57,0) -> 0
F58: 0 | G58: Single Fam Patch High | H58: 1000 | I58: =if(E58="Yes",H58*F58,0) -> 0
F59: 0 | G59: Single Fam Gut Rock/Tape Low | H59: 9000 | I59: =if(E59="Yes",H59*F59,0) -> 0
F60: 0 | G60: Single Fam Gut Rock/Tape High | H60: 10000 | I60: =if(E60="Yes",H60*F60,0) -> 0
F61: 0 | G61: Patch Area 10x10 | H61: 300 | I61: =if(E61="Yes",H61*F61,0) -> 0
A62: 23 | B62: Dumpsters | E62: No | F62: 1 | G62: Dumpster Low | H62: 500 | I62: =if(E62="Yes",H62*F62,0) -> 0
A63: 24 | B63: Decks | F63: 0 | G63: Dumpster High | H63: 600 | I63: =if(E63="Yes",H63*F63,0) -> 0
F64: 0 | G64: Single Family Patch 3 Dumps | H64: 1000 | I64: =if(E64="Yes",H64*F64,0) -> 0
F65: 0 | G65: Family Gut | H65: 3500 | I65: =if(E65="Yes",H65*F65,0) -> 0
F66: 0 | G66: Deck 10x10 | H66: 2000 | I66: =if(E66="Yes",H66*F66,0) -> 0
F67: 0 | G67: Deck 15x15 | H67: 3500 | I67: =if(E67="Yes",H67*F67,0) -> 0
G68: 3 Family w/ Fire Escape | H68: 5000 | I68: =if(E68="Yes",H68*F68,0) -> 0
A69: 25 | B69: Miscellaneous | F69: 0 | G69: # of Square Ft | H69: 0.5 | I69: =if(E69="Yes",H69*F69,0) -> 0

Sheet Definitions
A1: Section | B1: Name | C1: Definition
A2: Header | B2: Property Address: | C2: The address of the property you want to analyze
A3: Header | B3: Total Square Footage: | C3: The total square footage of the entire interior of the property
A4: Header | B4: Evaluator Name: | C4: Name of the evaluator.
A5: Header | B5: Property Description | C5: Key details and attributes about the property including differentiators, # of garage spaces, levels, layout, property type, etc.
A6: Property Values / Pricing | B6: Property Values / Pricing | C6: Section to enter property value and purchase figures for helping calculate profit
A7: Property Values / Pricing | B7: After Repair Value | C7: Value of the property after all repairs have been made regardless of purchase price. Also known as "Fair Market Value"
A8: Property Values / Pricing | B8: Current Value "As Is" | C8: Value of the property in current "as is" condition. Not factoring repairs needed.
A9: Property Values / Pricing | B9: Estimated Repair Costs | C9: The dollar amount of estimated repairs based on your analysis
A10: Property Values / Pricing | B10: Purchase Price | C10: The dollar amount you plan to purchase the property for
A11: Property Values / Pricing | B11: Estimated Hold Time months | C11: Estimated number of months you plan to own the property from purchase date to close of escrow sale date
A12: Financing Costs | B12: Financing Costs | C12: Section to enter the different amounts you will borrow to purchase the property.
... A61: Potential Return & Profit Analysis | B61: Total Costs Return on Investment ROI | C61: % of interest earned based on purchase +ALL costs regardless of how long the property was held

Sheet Table 1
A2: PROPERTY REPAIR ESTIMATE SHEET
A3: Property Address _____________________________________________________________ # of Bedrooms __________ # of Bathrooms __________ Square footage __________ .
A4: INSPECTION CHECKLIST | C4: Yes | D4: No | E4: Qty | F4: Average Price | G4: Comments | H4: Repair Cost
A5: Does the roof need to be replaced? | F5: $4/sqft
A6: Does the house need exterior paint? | F6: $4.50/sqft
A7: Do the windows need to be replaced? | F7: $400/unit
A8: Does the foundation need repair? | F8: $2.25/sqft
A9: Does the garage need any repairs? | F9: $500-$1500
A10: Does the yard require landscaping? | F10: 500
A11: Does the heating/plumbing need replacement? | F11: $2500-$3500
A12: Does the HVAC system need to be replaced? | F12: $1800-$2500
A13: Does the house need new duct work? | F13: $2.25/sqft
A14: Does the electrical system need to be updated? | F14: $2500-$4500
A15: Does the house need interior paint? | F15: $3.25/sqft
A16: Does the carpet need to be replaced? | F16: $1.25-$2.25/sqft
A17: Does the house need hardwood floors replaced? | F17: $6-8/sqft
A18: Does the kitchen require updates? | F18: $185/linear ft
A19: Does the kitchen need appliances? | F19: $2000-$3000
A20: Do the bathrooms need repair? | F20: $2500-$4500
A21: Does the basement need repair? | F21: varies
A22: Does the basement need waterproofing? | F22: $4000-$7000
A24: Miscellaneous
A25: Additional Comments
A26: .. | G26: TOTAL | H26: =SUM(H5:H22) -> 0
A27: After Repair Value ARV $_______________ Asking Price $ _________________ ARV x 70% - Assignment Fee = X $________________ $ X - Repairs = OFFER
A28: First Offer $_______________ Date_______________ First Counter $_______________ Date_______________ Second Offer $ _______________ Date_______________ Second Counter $_______________ Date________________
A31: DISCLAIMER: ALL VALUES IN AVERAGE PRICE COLUMN ARE MARKET DEPENDENT. PLEASE CONTACT LISCENSED PROFESSIONALS IN YOUR AREA FOR ACCURATE ANALYSIS AND QUOTES!

Sheet Amortization Schedule
D1: 1 | E1: 2 | F1: 3 | G1: 4 | H1: 5 | I1: 6 | J1: 7 | K1: 8 | L1: 9 | M1: 10 | N1: 11 | O1: 12 | Q1: Loan Amount | R1: =-B2 -> 500000 | T1: Make | U1: =C2
A2: Loan Amount | B2: -500000 | D2: 31 | E2: 28 | F2: 31 | G2: 30 | H2: 31 | I2: 30 | J2: 31 | K2: 31 | L2: 30 | M2: 31 | N2: 30 | O2: 31 | Q2: Interest Rate | R2: =B3 -> 0.03 | T2: Model | U2: =C3
A3: Interest Rate | B3: 0.03 | Q3: Loan Period | R3: =B4 -> 60 | T3: Year | U3: =C4
A4: Period | B4: 60 | D4: Months into Loan | E4: 21 | F4: 30 | G4: 45 | H4: 50 | I4: 55 | J4: 60 | Q4: Payment | R4: =B5 -> 8984.3453
A5: Payment | B5: =pmt(B3/12,B4,B2,0,0) -> 8984.3453 | D5: Loan Payoff Amount | E5: =VLOOKUP(E4,$B$9:$J$69,3) -> 341583.58 | F5: =VLOOKUP(F4,$B$9:$J$69,3) -> 267674.09 | G5: =VLOOKUP(G4,$B$9:$J$69,3) -> 140740.13 | H5: =VLOOKUP(H4,$B$9:$J$69,3) -> 97361.302 | I5: =VLOOKUP(I4,$B$9:$J$69,3) -> 53437.521 | J5: =VLOOKUP(J4,$B$9:$J$69,3) -> 8961.9405 | Q5: Monthly Insurance | R5: 300
A6: Monthly Ops Profit | B6: =(1000*4)-B5-250 -> -5234.3453 | D6: Realized Operating Profit Owner | E6: =$B$6*0.35*E$4 -> -38472.438 | F6: =$B$6*0.35*F4 -> -54960.626 | G6: =$B$6*0.35*G4 -> -82440.939 | H6: =$B$6*0.35*H4 -> -91601.043 | I6: =$B$6*0.35*I4 -> -100761.15 | J6: =$B$6*0.35*J4 -> -109921.25 | Q6: Monthly Revenue | R6: 15000
D7: Realized Operating Profit VDA | E7: =$B$6*0.65*E$4 -> -71448.814 | F7: =$B$6*0.65*F$4 -> -102069.73 | G7: =$B$6*0.65*G$4 -> -153104.6 | H7: =$B$6*0.65*H$4 -> -170116.22 | I7: =$B$6*0.65*I$4 -> -187127.85 | J7: =$B$6*0.65*J$4 -> -204139.47
A9: Day in the month | C9: Period | D9: Beginning Balance | E9: Payment | F9: Principal | G9: Interest | H9: Cumulative Principal | I9: Cumulative Interest | J9: Ending Balance | P9: Month #1 | Q9: Car Loan Patyment | R9: Insurance | S9: Revenue | T9: Profit | U9: Financial Risk | V9: Investor Profit | W9: VDA Profit
A10: =if(month($C10)=1,$D$2,if(month($C10)=2,$E$2,if(month($C10)=3,$F$2,if(month($C10)=4,$G$2,if(month($C10)=5,$H$2,if(month($C10)=6,$I$2,if(month($C10)=7,$J$2,if(month($C10)=8,$K$2,if(month($C10)=9,$L$2,if(month($C10)=10,$M$2,if(month($C10)=11,$N$2,if(month($C10)=12,$O$2)))))))))))) -> 30 | B10: 1 | C10: =today() -> 46279 | D10: =B2*-1 -> 500000 | E10: =$B$5 -> 8984.3453 | F10: =$E10-$G10 -> 7734.3453 | G10: =$D10*($B$3/12) -> 1250 | H10: 0 | I10: 0 | J10: =D10-F10 -> 492265.65 | P10: =B10 -> 1 | Q10: =E10 -> 8984.3453 | R10: =$R$5 -> 300 | S10: =$R$6 -> 15000 | T10: =S10-R10-Q10 -> 5715.6547 | U10: =J10 -> 492265.65 | V10: =T10*0.35 -> 2000.4791 | W10: =T10*0.65 -> 3715.1755
A11: =if(month($C11)=1,$D$2,if(month($C11)=2,$E$2,if(month($C11)=3,$F$2,if(month($C11)=4,$G$2,if(month($C11)=5,$H$2,if(month($C11)=6,$I$2,if(month($C11)=7,$J$2,if(month($C11)=8,$K$2,if(month($C11)=9,$L$2,if(month($C11)=10,$M$2,if(month($C11)=11,$N$2,if(month($C11)=12,$O$2)))))))))))) -> 31 | B11: 2 | C11: =C10+A10 -> 46309 | D11: =$J10 -> 492265.65 | E11: =$B$5 -> 8984.3453 | F11: =$E11-$G11 -> 7753.6812 | G11: =$D11*($B$3/12) -> 1230.6641 | H11: =F10+F11 -> 15488.027 | I11: =G10+G11 -> 2480.6641 | J11: =D11-F11 -> 484511.97 | P11: =B11 -> 2 | Q11: =E11 -> 8984.3453 | R11: =$R$5 -> 300 | S11: =$R$6 -> 15000 | T11: =S11-R11-Q11 -> 5715.6547 | U11: =J11 -> 484511.97 | V11: =T11*0.35 -> 2000.4791 | W11: =T11*0.65 -> 3715.1755
A12: =if(month($C12)=1,$D$2,if(month($C12)=2,$E$2,if(month($C12)=3,$F$2,if(month($C12)=4,$G$2,if(month($C12)=5,$H$2,if(month($C12)=6,$I$2,if(month($C12)=7,$J$2,if(month($C12)=8,$K$2,if(month($C12)=9,$L$2,if(month($C12)=10,$M$2,if(month($C12)=11,$N$2,if(month($C12)=12,$O$2)))))))))))) -> 30 | B12: 3 | C12: =C11+A11 -> 46340 | D12: =$J11 -> 484511.97 | E12: =$B$5 -> 8984.3453 | F12: =$E12-$G12 -> 7773.0654 | G12: =$D12*($B$3/12) -> 1211.2799 | H12: =H11+F12 -> 23261.092 | I12: =I11+G12 -> 3691.9441 | J12: =D12-F12 -> 476738.91 | P12: =B12 -> 3 | Q12: =E12 -> 8984.3453 | R12: =$R$5 -> 300 | S12: =$R$6 -> 15000 | T12: =S12-R12-Q12 -> 5715.6547 | U12: =J12 -> 476738.91 | V12: =T12*0.35 -> 2000.4791 | W12: =T12*0.65 -> 3715.1755
A13: =if(month($C13)=1,$D$2,if(month($C13)=2,$E$2,if(month($C13)=3,$F$2,if(month($C13)=4,$G$2,if(month($C13)=5,$H$2,if(month($C13)=6,$I$2,if(month($C13)=7,$J$2,if(month($C13)=8,$K$2,if(month($C13)=9,$L$2,if(month($C13)=10,$M$2,if(month($C13)=11,$N$2,if(month($C13)=12,$O$2)))))))))))) -> 31 | B13: 4 | C13: =C12+A12 -> 46370 | D13: =$J12 -> 476738.91 | E13: =$B$5 -> 8984.3453 | F13: =$E13-$G13 -> 7792.4981 | G13: =$D13*($B$3/12) -> 1191.8473 | H13: =H12+F13 -> 31053.59 | I13: =I12+G13 -> 4883.7913 | J13: =D13-F13 -> 468946.41 | P13: =B13 -> 4 | Q13: =E13 -> 8984.3453 | R13: =$R$5 -> 300 | S13: =$R$6 -> 15000 | T13: =S13-R13-Q13 -> 5715.6547 | U13: =J13 -> 468946.41 | V13: =T13*0.35 -> 2000.4791 | W13: =T13*0.65 -> 3715.1755
A14: =if(month($C14)=1,$D$2,if(month($C14)=2,$E$2,if(month($C14)=3,$F$2,if(month($C14)=4,$G$2,if(month($C14)=5,$H$2,if(month($C14)=6,$I$2,if(month($C14)=7,$J$2,if(month($C14)=8,$K$2,if(month($C14)=9,$L$2,if(month($C14)=10,$M$2,if(month($C14)=11,$N$2,if(month($C14)=12,$O$2)))))))))))) -> 31 | B14: 5 | C14: =C13+A13 -> 46401 | D14: =$J13 -> 468946.41 | E14: =$B$5 -> 8984.3453 | F14: =$E14-$G14 -> 7811.9793 | G14: =$D14*($B$3/12) -> 1172.366 | H14: =H13+F14 -> 38865.569 | I14: =I13+G14 -> 6056.1574 | J14: =D14-F14 -> 461134.43 | P14: =B14 -> 5 | Q14: =E14 -> 8984.3453 | R14: =$R$5 -> 300 | S14: =$R$6 -> 15000 | T14: =S14-R14-Q14 -> 5715.6547 | U14: =J14 -> 461134.43 | V14: =T14*0.35 -> 2000.4791 | W14: =T14*0.65 -> 3715.1755
A15: =if(month($C15)=1,$D$2,if(month($C15)=2,$E$2,if(month($C15)=3,$F$2,if(month($C15)=4,$G$2,if(month($C15)=5,$H$2,if(month($C15)=6,$I$2,if(month($C15)=7,$J$2,if(month($C15)=8,$K$2,if(month($C15)=9,$L$2,if(month($C15)=10,$M$2,if(month($C15)=11,$N$2,if(month($C15)=12,$O$2)))))))))))) -> 28 | B15: 6 | C15: =C14+A14 -> 46432 | D15: =$J14 -> 461134.43 | E15: =$B$5 -> 8984.3453 | F15: =$E15-$G15 -> 7831.5093 | G15: =$D15*($B$3/12) -> 1152.8361 | H15: =H14+F15 -> 46697.079 | I15: =I14+G15 -> 7208.9934 | J15: =D15-F15 -> 453302.92 | P15: =B15 -> 6 | Q15: =E15 -> 8984.3453 | R15: =$R$5 -> 300 | S15: =$R$6 -> 15000 | T15: =S15-R15-Q15 -> 5715.6547 | U15: =J15 -> 453302.92 | V15: =T15*0.35 -> 2000.4791 | W15: =T15*0.65 -> 3715.1755
A16: =if(month($C16)=1,$D$2,if(month($C16)=2,$E$2,if(month($C16)=3,$F$2,if(month($C16)=4,$G$2,if(month($C16)=5,$H$2,if(month($C16)=6,$I$2,if(month($C16)=7,$J$2,if(month($C16)=8,$K$2,if(month($C16)=9,$L$2,if(month($C16)=10,$M$2,if(month($C16)=11,$N$2,if(month($C16)=12,$O$2)))))))))))) -> 31 | B16: 7 | C16: =C15+A15 -> 46460 | D16: =$J15 -> 453302.92 | E16: =$B$5 -> 8984.3453 | F16: =$E16-$G16 -> 7851.088 | G16: =$D16*($B$3/12) -> 1133.2573 | H16: =H15+F16 -> 54548.167 | I16: =I15+G16 -> 8342.2507 | J16: =D16-F16 -> 445451.83 | P16: =B16 -> 7 | Q16: =E16 -> 8984.3453 | R16: =$R$5 -> 300 | S16: =$R$6 -> 15000 | T16: =S16-R16-Q16 -> 5715.6547 | U16: =J16 -> 445451.83 | V16: =T16*0.35 -> 2000.4791 | W16: =T16*0.65 -> 3715.1755
A17: =if(month($C17)=1,$D$2,if(month($C17)=2,$E$2,if(month($C17)=3,$F$2,if(month($C17)=4,$G$2,if(month($C17)=5,$H$2,if(month($C17)=6,$I$2,if(month($C17)=7,$J$2,if(month($C17)=8,$K$2,if(month($C17)=9,$L$2,if(month($C17)=10,$M$2,if(month($C17)=11,$N$2,if(month($C17)=12,$O$2)))))))))))) -> 30 | B17: 8 | C17: =C16+A16 -> 46491 | D17: =$J16 -> 445451.83 | E17: =$B$5 -> 8984.3453 | F17: =$E17-$G17 -> 7870.7157 | G17: =$D17*($B$3/12) -> 1113.6296 | H17: =H16+F17 -> 62418.882 | I17: =I16+G17 -> 9455.8803 | J17: =D17-F17 -> 437581.12 | P17: =B17 -> 8 | Q17: =E17 -> 8984.3453 | R17: =$R$5 -> 300 | S17: =$R$6 -> 15000 | T17: =S17-R17-Q17 -> 5715.6547 | U17: =J17 -> 437581.12 | V17: =T17*0.35 -> 2000.4791 | W17: =T17*0.65 -> 3715.1755
A18: =if(month($C18)=1,$D$2,if(month($C18)=2,$E$2,if(month($C18)=3,$F$2,if(month($C18)=4,$G$2,if(month($C18)=5,$H$2,if(month($C18)=6,$I$2,if(month($C18)=7,$J$2,if(month($C18)=8,$K$2,if(month($C18)=9,$L$2,if(month($C18)=10,$M$2,if(month($C18)=11,$N$2,if(month($C18)=12,$O$2)))))))))))) -> 31 | B18: 9 | C18: =C17+A17 -> 46521 | D18: =$J17 -> 437581.12 | E18: =$B$5 -> 8984.3453 | F18: =$E18-$G18 -> 7890.3925 | G18: =$D18*($B$3/12) -> 1093.9528 | H18: =H17+F18 -> 70309.275 | I18: =I17+G18 -> 10549.833 | J18: =D18-F18 -> 429690.73 | P18: =B18 -> 9 | Q18: =E18 -> 8984.3453 | R18: =$R$5 -> 300 | S18: =$R$6 -> 15000 | T18: =S18-R18-Q18 -> 5715.6547 | U18: =J18 -> 429690.73 | V18: =T18*0.35 -> 2000.4791 | W18: =T18*0.65 -> 3715.1755
A19: =if(month($C19)=1,$D$2,if(month($C19)=2,$E$2,if(month($C19)=3,$F$2,if(month($C19)=4,$G$2,if(month($C19)=5,$H$2,if(month($C19)=6,$I$2,if(month($C19)=7,$J$2,if(month($C19)=8,$K$2,if(month($C19)=9,$L$2,if(month($C19)=10,$M$2,if(month($C19)=11,$N$2,if(month($C19)=12,$O$2)))))))))))) -> 30 | B19: 10 | C19: =C18+A18 -> 46552 | D19: =$J18 -> 429690.73 | E19: =$B$5 -> 8984.3453 | F19: =$E19-$G19 -> 7910.1185 | G19: =$D19*($B$3/12) -> 1074.2268 | H19: =H18+F19 -> 78219.393 | I19: =I18+G19 -> 11624.06 | J19: =D19-F19 -> 421780.61 | P19: =B19 -> 10 | Q19: =E19 -> 8984.3453 | R19: =$R$5 -> 300 | S19: =$R$6 -> 15000 | T19: =S19-R19-Q19 -> 5715.6547 | U19: =J19 -> 421780.61 | V19: =T19*0.35 -> 2000.4791 | W19: =T19*0.65 -> 3715.1755
A20: =if(month($C20)=1,$D$2,if(month($C20)=2,$E$2,if(month($C20)=3,$F$2,if(month($C20)=4,$G$2,if(month($C20)=5,$H$2,if(month($C20)=6,$I$2,if(month($C20)=7,$J$2,if(month($C20)=8,$K$2,if(month($C20)=9,$L$2,if(month($C20)=10,$M$2,if(month($C20)=11,$N$2,if(month($C20)=12,$O$2)))))))))))) -> 31 | B20: 11 | C20: =C19+A19 -> 46582 | D20: =$J19 -> 421780.61 | E20: =$B$5 -> 8984.3453 | F20: =$E20-$G20 -> 7929.8938 | G20: =$D20*($B$3/12) -> 1054.4515 | H20: =H19+F20 -> 86149.287 | I20: =I19+G20 -> 12678.511 | J20: =D20-F20 -> 413850.71 | P20: =B20 -> 11 | Q20: =E20 -> 8984.3453 | R20: =$R$5 -> 300 | S20: =$R$6 -> 15000 | T20: =S20-R20-Q20 -> 5715.6547 | U20: =J20 -> 413850.71 | V20: =T20*0.35 -> 2000.4791 | W20: =T20*0.65 -> 3715.1755
A21: =if(month($C21)=1,$D$2,if(month($C21)=2,$E$2,if(month($C21)=3,$F$2,if(month($C21)=4,$G$2,if(month($C21)=5,$H$2,if(month($C21)=6,$I$2,if(month($C21)=7,$J$2,if(month($C21)=8,$K$2,if(month($C21)=9,$L$2,if(month($C21)=10,$M$2,if(month($C21)=11,$N$2,if(month($C21)=12,$O$2)))))))))))) -> 31 | B21: 12 | C21: =C20+A20 -> 46613 | D21: =$J20 -> 413850.71 | E21: =$B$5 -> 8984.3453 | F21: =$E21-$G21 -> 7949.7185 | G21: =$D21*($B$3/12) -> 1034.6268 | H21: =H20+F21 -> 94099.006 | I21: =I20+G21 -> 13713.138 | J21: =D21-F21 -> 405900.99 | P21: =B21 -> 12 | Q21: =E21 -> 8984.3453 | R21: =$R$5 -> 300 | S21: =$R$6 -> 15000 | T21: =S21-R21-Q21 -> 5715.6547 | U21: =J21 -> 405900.99 | V21: =T21*0.35 -> 2000.4791 | W21: =T21*0.65 -> 3715.1755
A22: =if(month($C22)=1,$D$2,if(month($C22)=2,$E$2,if(month($C22)=3,$F$2,if(month($C22)=4,$G$2,if(month($C22)=5,$H$2,if(month($C22)=6,$I$2,if(month($C22)=7,$J$2,if(month($C22)=8,$K$2,if(month($C22)=9,$L$2,if(month($C22)=10,$M$2,if(month($C22)=11,$N$2,if(month($C22)=12,$O$2)))))))))))) -> 30 | B22: 13 | C22: =C21+A21 -> 46644 | D22: =$J21 -> 405900.99 | E22: =$B$5 -> 8984.3453 | F22: =$E22-$G22 -> 7969.5928 | G22: =$D22*($B$3/12) -> 1014.7525 | H22: =H21+F22 -> 102068.6 | I22: =I21+G22 -> 14727.891 | J22: =D22-F22 -> 397931.4 | P22: =B22 -> 13 | Q22: =E22 -> 8984.3453 | R22: =$R$5 -> 300 | S22: =$R$6 -> 15000 | T22: =S22-R22-Q22 -> 5715.6547 | U22: =J22 -> 397931.4 | V22: =T22*0.35 -> 2000.4791 | W22: =T22*0.65 -> 3715.1755
A23: =if(month($C23)=1,$D$2,if(month($C23)=2,$E$2,if(month($C23)=3,$F$2,if(month($C23)=4,$G$2,if(month($C23)=5,$H$2,if(month($C23)=6,$I$2,if(month($C23)=7,$J$2,if(month($C23)=8,$K$2,if(month($C23)=9,$L$2,if(month($C23)=10,$M$2,if(month($C23)=11,$N$2,if(month($C23)=12,$O$2)))))))))))) -> 31 | B23: 14 | C23: =C22+A22 -> 46674 | D23: =$J22 -> 397931.4 | E23: =$B$5 -> 8984.3453 | F23: =$E23-$G23 -> 7989.5168 | G23: =$D23*($B$3/12) -> 994.8285 | H23: =H22+F23 -> 110058.12 | I23: =I22+G23 -> 15722.719 | J23: =D23-F23 -> 389941.88 | P23: =B23 -> 14 | Q23: =E23 -> 8984.3453 | R23: =$R$5 -> 300 | S23: =$R$6 -> 15000 | T23: =S23-R23-Q23 -> 5715.6547 | U23: =J23 -> 389941.88 | V23: =T23*0.35 -> 2000.4791 | W23: =T23*0.65 -> 3715.1755
... A69: =if(month($C69)=1,$D$2,if(month($C69)=2,$E$2,if(month($C69)=3,$F$2,if(month($C69)=4,$G$2,if(month($C69)=5,$H$2,if(month($C69)=6,$I$2,if(month($C69)=7,$J$2,if(month($C69)=8,$K$2,if(month($C69)=9,$L$2,if(month($C69)=10,$M$2,if(month($C69)=11,$N$2,if(month($C69)=12,$O$2)))))))))))) -> 31 | B69: 60 | C69: =C68+A68 -> 48073 | D69: =$J68 -> 8961.9405 | E69: =$B$5 -> 8984.3453 | F69: =$E69-$G69 -> 8961.9405 | G69: =$D69*($B$3/12) -> 22.404851 | H69: =H68+F69 -> 500000 | I69: =I68+G69 -> 39060.72 | J69: =D69-F69 -> -1.0984877e-08 | P69: =B69 -> 60 | Q69: =E69 -> 8984.3453 | R69: =$R$5 -> 300 | S69: =$R$6 -> 15000 | T69: =S69-R69-Q69 -> 5715.6547 | U69: =J69 -> -1.0984877e-08 | V69: =T69*0.35 -> 2000.4791 | W69: =T69*0.65 -> 3715.1755
R70: Total | S70: =sum(S10:S69) -> 900000 | T70: =sum(T10:T69) -> 342939.28 | V70: =sum(V10:V69) -> 120028.75 | W70: =sum(W10:W69) -> 222910.53
E71: Total | F71: =sum(F10:F69) -> 500000 | G71: =sum(G10:G69) -> 39060.72
